[
  {
    "signature": "async ExtractEventFromLogs({\n  \"abi\": [\n    {\n      \"constant\": true,\n      \"inputs\": [],\n      \"name\": \"STATUS_PUBLISHED\",\n      \"outputs\": [\n        {\n          \"name\": \"\",\n          \"type\": \"bytes32\"\n        }\n      ],\n      \"payable\": false,\n      \"stateMutability\": \"view\",\n      \"type\": \"function\"\n    },\n    {\n      \"constant\": true,\n      \"inputs\": [],\n      \"name\": \"creator\",\n      \"outputs\": [\n        {\n          \"name\": \"\",\n          \"type\": \"address\"\n        }\n      ],\n      \"payable\": false,\n      \"stateMutability\": \"view\",\n      \"type\": \"function\"\n    },\n    {\n      \"constant\": false,\n      \"inputs\": [],\n      \"name\": \"publish\",\n      \"outputs\": [\n        {\n          \"name\": \"\",\n          \"type\": \"bool\"\n        }\n      ],\n      \"payable\": true,\n      \"stateMutability\": \"payable\",\n      \"type\": \"function\"\n    },\n    {\n      \"constant\": true,\n      \"inputs\": [\n        {\n          \"name\": \"\",\n          \"type\": \"uint256\"\n        }\n      ],\n      \"name\": \"requestMap\",\n      \"outputs\": [\n        {\n          \"name\": \"originator\",\n          \"type\": \"address\"\n        },\n        {\n          \"name\": \"amountPaid\",\n          \"type\": \"uint256\"\n        },\n        {\n          \"name\": \"status\",\n          \"type\": \"int8\"\n        }\n      ],\n      \"payable\": false,\n      \"stateMutability\": \"view\",\n      \"type\": \"function\"\n    },\n    {\n      \"constant\": true,\n      \"inputs\": [],\n      \"name\": \"contentContractAddress\",\n      \"outputs\": [\n        {\n          \"name\": \"\",\n          \"type\": \"address\"\n        }\n      ],\n      \"payable\": false,\n      \"stateMutability\": \"view\",\n      \"type\": \"function\"\n    },\n    {\n      \"constant\": true,\n      \"inputs\": [],\n      \"name\": \"statusCode\",\n      \"outputs\": [\n        {\n          \"name\": \"\",\n          \"type\": \"int256\"\n        }\n      ],\n      \"payable\": false,\n      \"stateMutability\": \"view\",\n      \"type\": \"function\"\n    },\n    {\n      \"constant\": true,\n      \"inputs\": [],\n      \"name\": \"addressKMS\",\n      \"outputs\": [\n        {\n          \"name\": \"\",\n          \"type\": \"address\"\n        }\n      ],\n      \"payable\": false,\n      \"stateMutability\": \"view\",\n      \"type\": \"function\"\n    },\n    {\n      \"constant\": true,\n      \"inputs\": [],\n      \"name\": \"contentType\",\n      \"outputs\": [\n        {\n          \"name\": \"\",\n          \"type\": \"address\"\n        }\n      ],\n      \"payable\": false,\n      \"stateMutability\": \"view\",\n      \"type\": \"function\"\n    },\n    {\n      \"constant\": true,\n      \"inputs\": [\n        {\n          \"name\": \"status_code\",\n          \"type\": \"int256\"\n        }\n      ],\n      \"name\": \"statusCodeDescription\",\n      \"outputs\": [\n        {\n          \"name\": \"\",\n          \"type\": \"bytes32\"\n        }\n      ],\n      \"payable\": false,\n      \"stateMutability\": \"view\",\n      \"type\": \"function\"\n    },\n    {\n      \"constant\": false,\n      \"inputs\": [],\n      \"name\": \"kill\",\n      \"outputs\": [],\n      \"payable\": false,\n      \"stateMutability\": \"nonpayable\",\n      \"type\": \"function\"\n    },\n    {\n      \"constant\": true,\n      \"inputs\": [],\n      \"name\": \"STATUS_DRAFT\",\n      \"outputs\": [\n        {\n          \"name\": \"\",\n          \"type\": \"bytes32\"\n        }\n      ],\n      \"payable\": false,\n      \"stateMutability\": \"view\",\n      \"type\": \"function\"\n    },\n    {\n      \"constant\": false,\n      \"inputs\": [\n        {\n          \"name\": \"status_code\",\n          \"type\": \"int256\"\n        }\n      ],\n      \"name\": \"setStatusCode\",\n      \"outputs\": [\n        {\n          \"name\": \"\",\n          \"type\": \"int256\"\n        }\n      ],\n      \"payable\": false,\n      \"stateMutability\": \"nonpayable\",\n      \"type\": \"function\"\n    },\n    {\n      \"constant\": false,\n      \"inputs\": [\n        {\n          \"name\": \"request_ID\",\n          \"type\": \"uint256\"\n        },\n        {\n          \"name\": \"score_pct\",\n          \"type\": \"uint256\"\n        },\n        {\n          \"name\": \"ml_out_hash\",\n          \"type\": \"bytes32\"\n        }\n      ],\n      \"name\": \"accessComplete\",\n      \"outputs\": [\n        {\n          \"name\": \"\",\n          \"type\": \"bool\"\n        }\n      ],\n      \"payable\": true,\n      \"stateMutability\": \"payable\",\n      \"type\": \"function\"\n    },\n    {\n      \"constant\": true,\n      \"inputs\": [],\n      \"name\": \"accessCharge\",\n      \"outputs\": [\n        {\n          \"name\": \"\",\n          \"type\": \"uint256\"\n        }\n      ],\n      \"payable\": false,\n      \"stateMutability\": \"view\",\n      \"type\": \"function\"\n    },\n    {\n      \"constant\": false,\n      \"inputs\": [\n        {\n          \"name\": \"newCreator\",\n          \"type\": \"address\"\n        }\n      ],\n      \"name\": \"transferCreatorship\",\n      \"outputs\": [],\n      \"payable\": false,\n      \"stateMutability\": \"nonpayable\",\n      \"type\": \"function\"\n    },\n    {\n      \"constant\": false,\n      \"inputs\": [\n        {\n          \"name\": \"status_code\",\n          \"type\": \"int256\"\n        }\n      ],\n      \"name\": \"updateStatus\",\n      \"outputs\": [\n        {\n          \"name\": \"\",\n          \"type\": \"int256\"\n        }\n      ],\n      \"payable\": false,\n      \"stateMutability\": \"nonpayable\",\n      \"type\": \"function\"\n    },\n    {\n      \"constant\": false,\n      \"inputs\": [\n        {\n          \"name\": \"level\",\n          \"type\": \"uint8\"\n        },\n        {\n          \"name\": \"custom_values\",\n          \"type\": \"bytes32[]\"\n        },\n        {\n          \"name\": \"stakeholders\",\n          \"type\": \"address[]\"\n        }\n      ],\n      \"name\": \"getAccessCharge\",\n      \"outputs\": [\n        {\n          \"name\": \"\",\n          \"type\": \"uint256\"\n        }\n      ],\n      \"payable\": false,\n      \"stateMutability\": \"nonpayable\",\n      \"type\": \"function\"\n    },\n    {\n      \"constant\": true,\n      \"inputs\": [],\n      \"name\": \"owner\",\n      \"outputs\": [\n        {\n          \"name\": \"\",\n          \"type\": \"address\"\n        }\n      ],\n      \"payable\": false,\n      \"stateMutability\": \"view\",\n      \"type\": \"function\"\n    },\n    {\n      \"constant\": true,\n      \"inputs\": [],\n      \"name\": \"requestID\",\n      \"outputs\": [\n        {\n          \"name\": \"\",\n          \"type\": \"uint256\"\n        }\n      ],\n      \"payable\": false,\n      \"stateMutability\": \"view\",\n      \"type\": \"function\"\n    },\n    {\n      \"constant\": false,\n      \"inputs\": [\n        {\n          \"name\": \"level\",\n          \"type\": \"uint8\"\n        },\n        {\n          \"name\": \"pke_requestor\",\n          \"type\": \"string\"\n        },\n        {\n          \"name\": \"pke_AFGH\",\n          \"type\": \"string\"\n        },\n        {\n          \"name\": \"custom_values\",\n          \"type\": \"bytes32[]\"\n        },\n        {\n          \"name\": \"stakeholders\",\n          \"type\": \"address[]\"\n        }\n      ],\n      \"name\": \"accessRequest\",\n      \"outputs\": [\n        {\n          \"name\": \"\",\n          \"type\": \"bool\"\n        }\n      ],\n      \"payable\": true,\n      \"stateMutability\": \"payable\",\n      \"type\": \"function\"\n    },\n    {\n      \"constant\": true,\n      \"inputs\": [],\n      \"name\": \"libraryAddress\",\n      \"outputs\": [\n        {\n          \"name\": \"\",\n          \"type\": \"address\"\n        }\n      ],\n      \"payable\": false,\n      \"stateMutability\": \"view\",\n      \"type\": \"function\"\n    },\n    {\n      \"constant\": false,\n      \"inputs\": [],\n      \"name\": \"updateRequest\",\n      \"outputs\": [],\n      \"payable\": false,\n      \"stateMutability\": \"nonpayable\",\n      \"type\": \"function\"\n    },\n    {\n      \"constant\": false,\n      \"inputs\": [\n        {\n          \"name\": \"address_KMS\",\n          \"type\": \"address\"\n        }\n      ],\n      \"name\": \"setAddressKMS\",\n      \"outputs\": [],\n      \"payable\": false,\n      \"stateMutability\": \"nonpayable\",\n      \"type\": \"function\"\n    },\n    {\n      \"constant\": true,\n      \"inputs\": [],\n      \"name\": \"STATUS_REVIEW\",\n      \"outputs\": [\n        {\n          \"name\": \"\",\n          \"type\": \"bytes32\"\n        }\n      ],\n      \"payable\": false,\n      \"stateMutability\": \"view\",\n      \"type\": \"function\"\n    },\n    {\n      \"constant\": true,\n      \"inputs\": [],\n      \"name\": \"objectHash\",\n      \"outputs\": [\n        {\n          \"name\": \"\",\n          \"type\": \"bytes32\"\n        }\n      ],\n      \"payable\": false,\n      \"stateMutability\": \"view\",\n      \"type\": \"function\"\n    },\n    {\n      \"constant\": false,\n      \"inputs\": [\n        {\n          \"name\": \"addr\",\n          \"type\": \"address\"\n        }\n      ],\n      \"name\": \"setContentContractAddress\",\n      \"outputs\": [],\n      \"payable\": false,\n      \"stateMutability\": \"nonpayable\",\n      \"type\": \"function\"\n    },\n    {\n      \"constant\": false,\n      \"inputs\": [\n        {\n          \"name\": \"request_ID\",\n          \"type\": \"uint256\"\n        },\n        {\n          \"name\": \"access_granted\",\n          \"type\": \"bool\"\n        },\n        {\n          \"name\": \"re_key\",\n          \"type\": \"string\"\n        },\n        {\n          \"name\": \"encrypted_AES_key\",\n          \"type\": \"string\"\n        }\n      ],\n      \"name\": \"accessGrant\",\n      \"outputs\": [\n        {\n          \"name\": \"\",\n          \"type\": \"bool\"\n        }\n      ],\n      \"payable\": false,\n      \"stateMutability\": \"nonpayable\",\n      \"type\": \"function\"\n    },\n    {\n      \"constant\": false,\n      \"inputs\": [\n        {\n          \"name\": \"object_hash\",\n          \"type\": \"bytes32\"\n        }\n      ],\n      \"name\": \"commit\",\n      \"outputs\": [],\n      \"payable\": false,\n      \"stateMutability\": \"nonpayable\",\n      \"type\": \"function\"\n    },\n    {\n      \"constant\": false,\n      \"inputs\": [\n        {\n          \"name\": \"newOwner\",\n          \"type\": \"address\"\n        }\n      ],\n      \"name\": \"transferOwnership\",\n      \"outputs\": [],\n      \"payable\": false,\n      \"stateMutability\": \"nonpayable\",\n      \"type\": \"function\"\n    },\n    {\n      \"constant\": false,\n      \"inputs\": [\n        {\n          \"name\": \"charge\",\n          \"type\": \"uint256\"\n        }\n      ],\n      \"name\": \"setAccessCharge\",\n      \"outputs\": [\n        {\n          \"name\": \"\",\n          \"type\": \"uint256\"\n        }\n      ],\n      \"payable\": false,\n      \"stateMutability\": \"nonpayable\",\n      \"type\": \"function\"\n    },\n    {\n      \"constant\": true,\n      \"inputs\": [],\n      \"name\": \"statusDescription\",\n      \"outputs\": [\n        {\n          \"name\": \"\",\n          \"type\": \"bytes32\"\n        }\n      ],\n      \"payable\": false,\n      \"stateMutability\": \"view\",\n      \"type\": \"function\"\n    },\n    {\n      \"inputs\": [\n        {\n          \"name\": \"content_type\",\n          \"type\": \"address\"\n        }\n      ],\n      \"payable\": true,\n      \"stateMutability\": \"payable\",\n      \"type\": \"constructor\"\n    },\n    {\n      \"payable\": true,\n      \"stateMutability\": \"payable\",\n      \"type\": \"fallback\"\n    },\n    {\n      \"anonymous\": false,\n      \"inputs\": [\n        {\n          \"indexed\": false,\n          \"name\": \"containingLibrary\",\n          \"type\": \"address\"\n        }\n      ],\n      \"name\": \"ContentObjectCreate\",\n      \"type\": \"event\"\n    },\n    {\n      \"anonymous\": false,\n      \"inputs\": [\n        {\n          \"indexed\": false,\n          \"name\": \"contentType\",\n          \"type\": \"address\"\n        },\n        {\n          \"indexed\": false,\n          \"name\": \"contentContractAddress\",\n          \"type\": \"address\"\n        }\n      ],\n      \"name\": \"SetContentType\",\n      \"type\": \"event\"\n    },\n    {\n      \"anonymous\": false,\n      \"inputs\": [\n        {\n          \"indexed\": false,\n          \"name\": \"requestID\",\n          \"type\": \"uint256\"\n        },\n        {\n          \"indexed\": false,\n          \"name\": \"level\",\n          \"type\": \"uint8\"\n        },\n        {\n          \"indexed\": false,\n          \"name\": \"contentHash\",\n          \"type\": \"bytes32\"\n        },\n        {\n          \"indexed\": false,\n          \"name\": \"pkeRequestor\",\n          \"type\": \"string\"\n        },\n        {\n          \"indexed\": false,\n          \"name\": \"pkeAFGH\",\n          \"type\": \"string\"\n        }\n      ],\n      \"name\": \"AccessRequest\",\n      \"type\": \"event\"\n    },\n    {\n      \"anonymous\": false,\n      \"inputs\": [\n        {\n          \"indexed\": false,\n          \"name\": \"requestID\",\n          \"type\": \"uint256\"\n        },\n        {\n          \"indexed\": false,\n          \"name\": \"access_granted\",\n          \"type\": \"bool\"\n        },\n        {\n          \"indexed\": false,\n          \"name\": \"reKey\",\n          \"type\": \"string\"\n        },\n        {\n          \"indexed\": false,\n          \"name\": \"encryptedAESKey\",\n          \"type\": \"string\"\n        }\n      ],\n      \"name\": \"AccessGrant\",\n      \"type\": \"event\"\n    },\n    {\n      \"anonymous\": false,\n      \"inputs\": [\n        {\n          \"indexed\": false,\n          \"name\": \"customValue\",\n          \"type\": \"bytes32\"\n        }\n      ],\n      \"name\": \"AccessRequestValue\",\n      \"type\": \"event\"\n    },\n    {\n      \"anonymous\": false,\n      \"inputs\": [\n        {\n          \"indexed\": false,\n          \"name\": \"stakeholder\",\n          \"type\": \"address\"\n        }\n      ],\n      \"name\": \"AccessRequestStakeholder\",\n      \"type\": \"event\"\n    },\n    {\n      \"anonymous\": false,\n      \"inputs\": [\n        {\n          \"indexed\": false,\n          \"name\": \"requestID\",\n          \"type\": \"uint256\"\n        },\n        {\n          \"indexed\": false,\n          \"name\": \"scorePct\",\n          \"type\": \"uint256\"\n        },\n        {\n          \"indexed\": false,\n          \"name\": \"mlOutHash\",\n          \"type\": \"bytes32\"\n        },\n        {\n          \"indexed\": false,\n          \"name\": \"customContractResult\",\n          \"type\": \"bool\"\n        }\n      ],\n      \"name\": \"AccessComplete\",\n      \"type\": \"event\"\n    },\n    {\n      \"anonymous\": false,\n      \"inputs\": [\n        {\n          \"indexed\": false,\n          \"name\": \"contentContractAddress\",\n          \"type\": \"address\"\n        }\n      ],\n      \"name\": \"SetContentContract\",\n      \"type\": \"event\"\n    },\n    {\n      \"anonymous\": false,\n      \"inputs\": [\n        {\n          \"indexed\": false,\n          \"name\": \"accessCharge\",\n          \"type\": \"uint256\"\n        }\n      ],\n      \"name\": \"SetAccessCharge\",\n      \"type\": \"event\"\n    },\n    {\n      \"anonymous\": false,\n      \"inputs\": [\n        {\n          \"indexed\": false,\n          \"name\": \"level\",\n          \"type\": \"uint8\"\n        },\n        {\n          \"indexed\": false,\n          \"name\": \"accessCharge\",\n          \"type\": \"uint256\"\n        }\n      ],\n      \"name\": \"GetAccessCharge\",\n      \"type\": \"event\"\n    },\n    {\n      \"anonymous\": false,\n      \"inputs\": [\n        {\n          \"indexed\": false,\n          \"name\": \"accessCharge\",\n          \"type\": \"uint256\"\n        },\n        {\n          \"indexed\": false,\n          \"name\": \"amountProvided\",\n          \"type\": \"uint256\"\n        }\n      ],\n      \"name\": \"InsufficientFunds\",\n      \"type\": \"event\"\n    },\n    {\n      \"anonymous\": false,\n      \"inputs\": [\n        {\n          \"indexed\": false,\n          \"name\": \"statusCode\",\n          \"type\": \"int256\"\n        }\n      ],\n      \"name\": \"SetStatusCode\",\n      \"type\": \"event\"\n    },\n    {\n      \"anonymous\": false,\n      \"inputs\": [\n        {\n          \"indexed\": false,\n          \"name\": \"requestStatus\",\n          \"type\": \"bool\"\n        },\n        {\n          \"indexed\": false,\n          \"name\": \"statusCode\",\n          \"type\": \"int256\"\n        },\n        {\n          \"indexed\": false,\n          \"name\": \"objectHash\",\n          \"type\": \"bytes32\"\n        }\n      ],\n      \"name\": \"Publish\",\n      \"type\": \"event\"\n    },\n    {\n      \"anonymous\": false,\n      \"inputs\": [\n        {\n          \"indexed\": false,\n          \"name\": \"custom_contract\",\n          \"type\": \"address\"\n        }\n      ],\n      \"name\": \"InvokeCustomPreHook\",\n      \"type\": \"event\"\n    },\n    {\n      \"anonymous\": false,\n      \"inputs\": [\n        {\n          \"indexed\": false,\n          \"name\": \"custom_contract\",\n          \"type\": \"address\"\n        },\n        {\n          \"indexed\": false,\n          \"name\": \"result\",\n          \"type\": \"uint256\"\n        }\n      ],\n      \"name\": \"ReturnCustomHook\",\n      \"type\": \"event\"\n    },\n    {\n      \"anonymous\": false,\n      \"inputs\": [\n        {\n          \"indexed\": false,\n          \"name\": \"custom_contract\",\n          \"type\": \"address\"\n        }\n      ],\n      \"name\": \"InvokeCustomPostHook\",\n      \"type\": \"event\"\n    },\n    {\n      \"anonymous\": false,\n      \"inputs\": [\n        {\n          \"indexed\": false,\n          \"name\": \"objectHash\",\n          \"type\": \"bytes32\"\n        }\n      ],\n      \"name\": \"Commit\",\n      \"type\": \"event\"\n    },\n    {\n      \"anonymous\": false,\n      \"inputs\": [\n        {\n          \"indexed\": false,\n          \"name\": \"objectHash\",\n          \"type\": \"bytes32\"\n        }\n      ],\n      \"name\": \"UpdateRequest\",\n      \"type\": \"event\"\n    }\n  ],\n  \"event\": {\n    \"to\": \"0x3F0AD83d1e0Ae510eb7764B52Ef21be12BEB7d3C\",\n    \"from\": \"0xf7C6072c6d61305000E33fF8D8735b3C6af7e10D\",\n    \"contractAddress\": null,\n    \"transactionIndex\": 0,\n    \"root\": \"0x0763c27a9923c8a8c2d8a54b646ef83576846450b1a8328661c2760c16f39df3\",\n    \"gasUsed\": {\n      \"_hex\": \"0x16e54\"\n    },\n    \"logsBloom\": \"0x00000000000000000000000000000000000000000000000000000000000000000000000000000000000000000000000000000000000000000000000000000000000000000000000004000000000000000000000000000000000000000000000000400000000000000000000000000000000000000000000000000000000000000000000000000000000000000200000000000000000000000000000000000000000000000000000000000000000000000000000000000000000000000000000000000000000000000000000000000000000000080000000000000000008000000000000000000000000000000000000000000000000000000000002000000000\",\n    \"blockHash\": \"0xf7ce95848d6fd1f1ea07547b0272af7e2015016a83ea0299a2226b1beb0e8541\",\n    \"transactionHash\": \"0x0d3a948edca9419a0db99fbfd556d7288225d12c37650e0454c28fd02a83d274\",\n    \"logs\": [\n      {\n        \"transactionIndex\": 0,\n        \"blockNumber\": 67234,\n        \"transactionHash\": \"0x0d3a948edca9419a0db99fbfd556d7288225d12c37650e0454c28fd02a83d274\",\n        \"address\": \"0x3F0AD83d1e0Ae510eb7764B52Ef21be12BEB7d3C\",\n        \"topics\": [\n          \"0x089a6f1788a3c353423e1be4ba12533bdde7d908bb41abeee185af0acb3df562\"\n        ],\n        \"data\": \"0x00000000000000000000000000000000000000000000000000000000000000010000000000000000000000000000000000000000000000000000000000000000000000000000000000000000000000000000000000000000000000000000000000000000000000000000000000000000000000000000000000000000000000a000000000000000000000000000000000000000000000000000000000000001600000000000000000000000000000000000000000000000000000000000000084307830343036343864643165323761396261336131393937323766343864323765373139363363303465356164363334386337383864626635346236373733663933396437663933396437343932616163613137613731646233393630376664333436383561306639353564353234353961323130386533376364663030373834616532000000000000000000000000000000000000000000000000000000000000000000000000000000000000000000000000000000000000000000000000\",\n        \"logIndex\": 0,\n        \"blockHash\": \"0xf7ce95848d6fd1f1ea07547b0272af7e2015016a83ea0299a2226b1beb0e8541\",\n        \"transactionLogIndex\": 0,\n        \"name\": \"AccessRequest\",\n        \"signature\": \"AccessRequest(uint256,uint8,bytes32,string,string)\",\n        \"topic\": \"0x089a6f1788a3c353423e1be4ba12533bdde7d908bb41abeee185af0acb3df562\",\n        \"values\": {\n          \"0\": {\n            \"_hex\": \"0x01\"\n          },\n          \"1\": 0,\n          \"2\": \"0x0000000000000000000000000000000000000000000000000000000000000000\",\n          \"3\": \"0x040648dd1e27a9ba3a199727f48d27e71963c04e5ad6348c788dbf54b6773f939d7f939d7492aaca17a71db39607fd34685a0f955d52459a2108e37cdf00784ae2\",\n          \"4\": \"\",\n          \"requestID\": {\n            \"_hex\": \"0x01\"\n          },\n          \"level\": 0,\n          \"contentHash\": \"0x0000000000000000000000000000000000000000000000000000000000000000\",\n          \"pkeRequestor\": \"0x040648dd1e27a9ba3a199727f48d27e71963c04e5ad6348c788dbf54b6773f939d7f939d7492aaca17a71db39607fd34685a0f955d52459a2108e37cdf00784ae2\",\n          \"pkeAFGH\": \"\",\n          \"length\": 5\n        }\n      }\n    ],\n    \"blockNumber\": 67234,\n    \"confirmations\": 1,\n    \"cumulativeGasUsed\": {\n      \"_hex\": \"0x16e54\"\n    }\n  },\n  \"eventName\": \"AccessRequest\"\n});",
    "result": {
      "name": "AccessRequest",
      "signature": "AccessRequest(uint256,uint8,bytes32,string,string)",
      "topic": "0x089a6f1788a3c353423e1be4ba12533bdde7d908bb41abeee185af0acb3df562",
      "values": {
        "0": {
          "_hex": "0x01"
        },
        "1": 0,
        "2": "0x0000000000000000000000000000000000000000000000000000000000000000",
        "3": "0x040648dd1e27a9ba3a199727f48d27e71963c04e5ad6348c788dbf54b6773f939d7f939d7492aaca17a71db39607fd34685a0f955d52459a2108e37cdf00784ae2",
        "4": "",
        "requestID": {
          "_hex": "0x01"
        },
        "level": 0,
        "contentHash": "0x0000000000000000000000000000000000000000000000000000000000000000",
        "pkeRequestor": "0x040648dd1e27a9ba3a199727f48d27e71963c04e5ad6348c788dbf54b6773f939d7f939d7492aaca17a71db39607fd34685a0f955d52459a2108e37cdf00784ae2",
        "pkeAFGH": "",
        "length": 5
      }
    }
  },
  {
    "signature": "async ExtractEventFromLogs({\n  \"abi\": [\n    {\n      \"constant\": true,\n      \"inputs\": [],\n      \"name\": \"STATUS_PUBLISHED\",\n      \"outputs\": [\n        {\n          \"name\": \"\",\n          \"type\": \"bytes32\"\n        }\n      ],\n      \"payable\": false,\n      \"stateMutability\": \"view\",\n      \"type\": \"function\"\n    },\n    {\n      \"constant\": true,\n      \"inputs\": [],\n      \"name\": \"creator\",\n      \"outputs\": [\n        {\n          \"name\": \"\",\n          \"type\": \"address\"\n        }\n      ],\n      \"payable\": false,\n      \"stateMutability\": \"view\",\n      \"type\": \"function\"\n    },\n    {\n      \"constant\": false,\n      \"inputs\": [],\n      \"name\": \"publish\",\n      \"outputs\": [\n        {\n          \"name\": \"\",\n          \"type\": \"bool\"\n        }\n      ],\n      \"payable\": true,\n      \"stateMutability\": \"payable\",\n      \"type\": \"function\"\n    },\n    {\n      \"constant\": true,\n      \"inputs\": [\n        {\n          \"name\": \"\",\n          \"type\": \"uint256\"\n        }\n      ],\n      \"name\": \"requestMap\",\n      \"outputs\": [\n        {\n          \"name\": \"originator\",\n          \"type\": \"address\"\n        },\n        {\n          \"name\": \"amountPaid\",\n          \"type\": \"uint256\"\n        },\n        {\n          \"name\": \"status\",\n          \"type\": \"int8\"\n        }\n      ],\n      \"payable\": false,\n      \"stateMutability\": \"view\",\n      \"type\": \"function\"\n    },\n    {\n      \"constant\": true,\n      \"inputs\": [],\n      \"name\": \"contentContractAddress\",\n      \"outputs\": [\n        {\n          \"name\": \"\",\n          \"type\": \"address\"\n        }\n      ],\n      \"payable\": false,\n      \"stateMutability\": \"view\",\n      \"type\": \"function\"\n    },\n    {\n      \"constant\": true,\n      \"inputs\": [],\n      \"name\": \"statusCode\",\n      \"outputs\": [\n        {\n          \"name\": \"\",\n          \"type\": \"int256\"\n        }\n      ],\n      \"payable\": false,\n      \"stateMutability\": \"view\",\n      \"type\": \"function\"\n    },\n    {\n      \"constant\": true,\n      \"inputs\": [],\n      \"name\": \"addressKMS\",\n      \"outputs\": [\n        {\n          \"name\": \"\",\n          \"type\": \"address\"\n        }\n      ],\n      \"payable\": false,\n      \"stateMutability\": \"view\",\n      \"type\": \"function\"\n    },\n    {\n      \"constant\": true,\n      \"inputs\": [],\n      \"name\": \"contentType\",\n      \"outputs\": [\n        {\n          \"name\": \"\",\n          \"type\": \"address\"\n        }\n      ],\n      \"payable\": false,\n      \"stateMutability\": \"view\",\n      \"type\": \"function\"\n    },\n    {\n      \"constant\": true,\n      \"inputs\": [\n        {\n          \"name\": \"status_code\",\n          \"type\": \"int256\"\n        }\n      ],\n      \"name\": \"statusCodeDescription\",\n      \"outputs\": [\n        {\n          \"name\": \"\",\n          \"type\": \"bytes32\"\n        }\n      ],\n      \"payable\": false,\n      \"stateMutability\": \"view\",\n      \"type\": \"function\"\n    },\n    {\n      \"constant\": false,\n      \"inputs\": [],\n      \"name\": \"kill\",\n      \"outputs\": [],\n      \"payable\": false,\n      \"stateMutability\": \"nonpayable\",\n      \"type\": \"function\"\n    },\n    {\n      \"constant\": true,\n      \"inputs\": [],\n      \"name\": \"STATUS_DRAFT\",\n      \"outputs\": [\n        {\n          \"name\": \"\",\n          \"type\": \"bytes32\"\n        }\n      ],\n      \"payable\": false,\n      \"stateMutability\": \"view\",\n      \"type\": \"function\"\n    },\n    {\n      \"constant\": false,\n      \"inputs\": [\n        {\n          \"name\": \"status_code\",\n          \"type\": \"int256\"\n        }\n      ],\n      \"name\": \"setStatusCode\",\n      \"outputs\": [\n        {\n          \"name\": \"\",\n          \"type\": \"int256\"\n        }\n      ],\n      \"payable\": false,\n      \"stateMutability\": \"nonpayable\",\n      \"type\": \"function\"\n    },\n    {\n      \"constant\": false,\n      \"inputs\": [\n        {\n          \"name\": \"request_ID\",\n          \"type\": \"uint256\"\n        },\n        {\n          \"name\": \"score_pct\",\n          \"type\": \"uint256\"\n        },\n        {\n          \"name\": \"ml_out_hash\",\n          \"type\": \"bytes32\"\n        }\n      ],\n      \"name\": \"accessComplete\",\n      \"outputs\": [\n        {\n          \"name\": \"\",\n          \"type\": \"bool\"\n        }\n      ],\n      \"payable\": true,\n      \"stateMutability\": \"payable\",\n      \"type\": \"function\"\n    },\n    {\n      \"constant\": true,\n      \"inputs\": [],\n      \"name\": \"accessCharge\",\n      \"outputs\": [\n        {\n          \"name\": \"\",\n          \"type\": \"uint256\"\n        }\n      ],\n      \"payable\": false,\n      \"stateMutability\": \"view\",\n      \"type\": \"function\"\n    },\n    {\n      \"constant\": false,\n      \"inputs\": [\n        {\n          \"name\": \"newCreator\",\n          \"type\": \"address\"\n        }\n      ],\n      \"name\": \"transferCreatorship\",\n      \"outputs\": [],\n      \"payable\": false,\n      \"stateMutability\": \"nonpayable\",\n      \"type\": \"function\"\n    },\n    {\n      \"constant\": false,\n      \"inputs\": [\n        {\n          \"name\": \"status_code\",\n          \"type\": \"int256\"\n        }\n      ],\n      \"name\": \"updateStatus\",\n      \"outputs\": [\n        {\n          \"name\": \"\",\n          \"type\": \"int256\"\n        }\n      ],\n      \"payable\": false,\n      \"stateMutability\": \"nonpayable\",\n      \"type\": \"function\"\n    },\n    {\n      \"constant\": false,\n      \"inputs\": [\n        {\n          \"name\": \"level\",\n          \"type\": \"uint8\"\n        },\n        {\n          \"name\": \"custom_values\",\n          \"type\": \"bytes32[]\"\n        },\n        {\n          \"name\": \"stakeholders\",\n          \"type\": \"address[]\"\n        }\n      ],\n      \"name\": \"getAccessCharge\",\n      \"outputs\": [\n        {\n          \"name\": \"\",\n          \"type\": \"uint256\"\n        }\n      ],\n      \"payable\": false,\n      \"stateMutability\": \"nonpayable\",\n      \"type\": \"function\"\n    },\n    {\n      \"constant\": true,\n      \"inputs\": [],\n      \"name\": \"owner\",\n      \"outputs\": [\n        {\n          \"name\": \"\",\n          \"type\": \"address\"\n        }\n      ],\n      \"payable\": false,\n      \"stateMutability\": \"view\",\n      \"type\": \"function\"\n    },\n    {\n      \"constant\": true,\n      \"inputs\": [],\n      \"name\": \"requestID\",\n      \"outputs\": [\n        {\n          \"name\": \"\",\n          \"type\": \"uint256\"\n        }\n      ],\n      \"payable\": false,\n      \"stateMutability\": \"view\",\n      \"type\": \"function\"\n    },\n    {\n      \"constant\": false,\n      \"inputs\": [\n        {\n          \"name\": \"level\",\n          \"type\": \"uint8\"\n        },\n        {\n          \"name\": \"pke_requestor\",\n          \"type\": \"string\"\n        },\n        {\n          \"name\": \"pke_AFGH\",\n          \"type\": \"string\"\n        },\n        {\n          \"name\": \"custom_values\",\n          \"type\": \"bytes32[]\"\n        },\n        {\n          \"name\": \"stakeholders\",\n          \"type\": \"address[]\"\n        }\n      ],\n      \"name\": \"accessRequest\",\n      \"outputs\": [\n        {\n          \"name\": \"\",\n          \"type\": \"bool\"\n        }\n      ],\n      \"payable\": true,\n      \"stateMutability\": \"payable\",\n      \"type\": \"function\"\n    },\n    {\n      \"constant\": true,\n      \"inputs\": [],\n      \"name\": \"libraryAddress\",\n      \"outputs\": [\n        {\n          \"name\": \"\",\n          \"type\": \"address\"\n        }\n      ],\n      \"payable\": false,\n      \"stateMutability\": \"view\",\n      \"type\": \"function\"\n    },\n    {\n      \"constant\": false,\n      \"inputs\": [],\n      \"name\": \"updateRequest\",\n      \"outputs\": [],\n      \"payable\": false,\n      \"stateMutability\": \"nonpayable\",\n      \"type\": \"function\"\n    },\n    {\n      \"constant\": false,\n      \"inputs\": [\n        {\n          \"name\": \"address_KMS\",\n          \"type\": \"address\"\n        }\n      ],\n      \"name\": \"setAddressKMS\",\n      \"outputs\": [],\n      \"payable\": false,\n      \"stateMutability\": \"nonpayable\",\n      \"type\": \"function\"\n    },\n    {\n      \"constant\": true,\n      \"inputs\": [],\n      \"name\": \"STATUS_REVIEW\",\n      \"outputs\": [\n        {\n          \"name\": \"\",\n          \"type\": \"bytes32\"\n        }\n      ],\n      \"payable\": false,\n      \"stateMutability\": \"view\",\n      \"type\": \"function\"\n    },\n    {\n      \"constant\": true,\n      \"inputs\": [],\n      \"name\": \"objectHash\",\n      \"outputs\": [\n        {\n          \"name\": \"\",\n          \"type\": \"bytes32\"\n        }\n      ],\n      \"payable\": false,\n      \"stateMutability\": \"view\",\n      \"type\": \"function\"\n    },\n    {\n      \"constant\": false,\n      \"inputs\": [\n        {\n          \"name\": \"addr\",\n          \"type\": \"address\"\n        }\n      ],\n      \"name\": \"setContentContractAddress\",\n      \"outputs\": [],\n      \"payable\": false,\n      \"stateMutability\": \"nonpayable\",\n      \"type\": \"function\"\n    },\n    {\n      \"constant\": false,\n      \"inputs\": [\n        {\n          \"name\": \"request_ID\",\n          \"type\": \"uint256\"\n        },\n        {\n          \"name\": \"access_granted\",\n          \"type\": \"bool\"\n        },\n        {\n          \"name\": \"re_key\",\n          \"type\": \"string\"\n        },\n        {\n          \"name\": \"encrypted_AES_key\",\n          \"type\": \"string\"\n        }\n      ],\n      \"name\": \"accessGrant\",\n      \"outputs\": [\n        {\n          \"name\": \"\",\n          \"type\": \"bool\"\n        }\n      ],\n      \"payable\": false,\n      \"stateMutability\": \"nonpayable\",\n      \"type\": \"function\"\n    },\n    {\n      \"constant\": false,\n      \"inputs\": [\n        {\n          \"name\": \"object_hash\",\n          \"type\": \"bytes32\"\n        }\n      ],\n      \"name\": \"commit\",\n      \"outputs\": [],\n      \"payable\": false,\n      \"stateMutability\": \"nonpayable\",\n      \"type\": \"function\"\n    },\n    {\n      \"constant\": false,\n      \"inputs\": [\n        {\n          \"name\": \"newOwner\",\n          \"type\": \"address\"\n        }\n      ],\n      \"name\": \"transferOwnership\",\n      \"outputs\": [],\n      \"payable\": false,\n      \"stateMutability\": \"nonpayable\",\n      \"type\": \"function\"\n    },\n    {\n      \"constant\": false,\n      \"inputs\": [\n        {\n          \"name\": \"charge\",\n          \"type\": \"uint256\"\n        }\n      ],\n      \"name\": \"setAccessCharge\",\n      \"outputs\": [\n        {\n          \"name\": \"\",\n          \"type\": \"uint256\"\n        }\n      ],\n      \"payable\": false,\n      \"stateMutability\": \"nonpayable\",\n      \"type\": \"function\"\n    },\n    {\n      \"constant\": true,\n      \"inputs\": [],\n      \"name\": \"statusDescription\",\n      \"outputs\": [\n        {\n          \"name\": \"\",\n          \"type\": \"bytes32\"\n        }\n      ],\n      \"payable\": false,\n      \"stateMutability\": \"view\",\n      \"type\": \"function\"\n    },\n    {\n      \"inputs\": [\n        {\n          \"name\": \"content_type\",\n          \"type\": \"address\"\n        }\n      ],\n      \"payable\": true,\n      \"stateMutability\": \"payable\",\n      \"type\": \"constructor\"\n    },\n    {\n      \"payable\": true,\n      \"stateMutability\": \"payable\",\n      \"type\": \"fallback\"\n    },\n    {\n      \"anonymous\": false,\n      \"inputs\": [\n        {\n          \"indexed\": false,\n          \"name\": \"containingLibrary\",\n          \"type\": \"address\"\n        }\n      ],\n      \"name\": \"ContentObjectCreate\",\n      \"type\": \"event\"\n    },\n    {\n      \"anonymous\": false,\n      \"inputs\": [\n        {\n          \"indexed\": false,\n          \"name\": \"contentType\",\n          \"type\": \"address\"\n        },\n        {\n          \"indexed\": false,\n          \"name\": \"contentContractAddress\",\n          \"type\": \"address\"\n        }\n      ],\n      \"name\": \"SetContentType\",\n      \"type\": \"event\"\n    },\n    {\n      \"anonymous\": false,\n      \"inputs\": [\n        {\n          \"indexed\": false,\n          \"name\": \"requestID\",\n          \"type\": \"uint256\"\n        },\n        {\n          \"indexed\": false,\n          \"name\": \"level\",\n          \"type\": \"uint8\"\n        },\n        {\n          \"indexed\": false,\n          \"name\": \"contentHash\",\n          \"type\": \"bytes32\"\n        },\n        {\n          \"indexed\": false,\n          \"name\": \"pkeRequestor\",\n          \"type\": \"string\"\n        },\n        {\n          \"indexed\": false,\n          \"name\": \"pkeAFGH\",\n          \"type\": \"string\"\n        }\n      ],\n      \"name\": \"AccessRequest\",\n      \"type\": \"event\"\n    },\n    {\n      \"anonymous\": false,\n      \"inputs\": [\n        {\n          \"indexed\": false,\n          \"name\": \"requestID\",\n          \"type\": \"uint256\"\n        },\n        {\n          \"indexed\": false,\n          \"name\": \"access_granted\",\n          \"type\": \"bool\"\n        },\n        {\n          \"indexed\": false,\n          \"name\": \"reKey\",\n          \"type\": \"string\"\n        },\n        {\n          \"indexed\": false,\n          \"name\": \"encryptedAESKey\",\n          \"type\": \"string\"\n        }\n      ],\n      \"name\": \"AccessGrant\",\n      \"type\": \"event\"\n    },\n    {\n      \"anonymous\": false,\n      \"inputs\": [\n        {\n          \"indexed\": false,\n          \"name\": \"customValue\",\n          \"type\": \"bytes32\"\n        }\n      ],\n      \"name\": \"AccessRequestValue\",\n      \"type\": \"event\"\n    },\n    {\n      \"anonymous\": false,\n      \"inputs\": [\n        {\n          \"indexed\": false,\n          \"name\": \"stakeholder\",\n          \"type\": \"address\"\n        }\n      ],\n      \"name\": \"AccessRequestStakeholder\",\n      \"type\": \"event\"\n    },\n    {\n      \"anonymous\": false,\n      \"inputs\": [\n        {\n          \"indexed\": false,\n          \"name\": \"requestID\",\n          \"type\": \"uint256\"\n        },\n        {\n          \"indexed\": false,\n          \"name\": \"scorePct\",\n          \"type\": \"uint256\"\n        },\n        {\n          \"indexed\": false,\n          \"name\": \"mlOutHash\",\n          \"type\": \"bytes32\"\n        },\n        {\n          \"indexed\": false,\n          \"name\": \"customContractResult\",\n          \"type\": \"bool\"\n        }\n      ],\n      \"name\": \"AccessComplete\",\n      \"type\": \"event\"\n    },\n    {\n      \"anonymous\": false,\n      \"inputs\": [\n        {\n          \"indexed\": false,\n          \"name\": \"contentContractAddress\",\n          \"type\": \"address\"\n        }\n      ],\n      \"name\": \"SetContentContract\",\n      \"type\": \"event\"\n    },\n    {\n      \"anonymous\": false,\n      \"inputs\": [\n        {\n          \"indexed\": false,\n          \"name\": \"accessCharge\",\n          \"type\": \"uint256\"\n        }\n      ],\n      \"name\": \"SetAccessCharge\",\n      \"type\": \"event\"\n    },\n    {\n      \"anonymous\": false,\n      \"inputs\": [\n        {\n          \"indexed\": false,\n          \"name\": \"level\",\n          \"type\": \"uint8\"\n        },\n        {\n          \"indexed\": false,\n          \"name\": \"accessCharge\",\n          \"type\": \"uint256\"\n        }\n      ],\n      \"name\": \"GetAccessCharge\",\n      \"type\": \"event\"\n    },\n    {\n      \"anonymous\": false,\n      \"inputs\": [\n        {\n          \"indexed\": false,\n          \"name\": \"accessCharge\",\n          \"type\": \"uint256\"\n        },\n        {\n          \"indexed\": false,\n          \"name\": \"amountProvided\",\n          \"type\": \"uint256\"\n        }\n      ],\n      \"name\": \"InsufficientFunds\",\n      \"type\": \"event\"\n    },\n    {\n      \"anonymous\": false,\n      \"inputs\": [\n        {\n          \"indexed\": false,\n          \"name\": \"statusCode\",\n          \"type\": \"int256\"\n        }\n      ],\n      \"name\": \"SetStatusCode\",\n      \"type\": \"event\"\n    },\n    {\n      \"anonymous\": false,\n      \"inputs\": [\n        {\n          \"indexed\": false,\n          \"name\": \"requestStatus\",\n          \"type\": \"bool\"\n        },\n        {\n          \"indexed\": false,\n          \"name\": \"statusCode\",\n          \"type\": \"int256\"\n        },\n        {\n          \"indexed\": false,\n          \"name\": \"objectHash\",\n          \"type\": \"bytes32\"\n        }\n      ],\n      \"name\": \"Publish\",\n      \"type\": \"event\"\n    },\n    {\n      \"anonymous\": false,\n      \"inputs\": [\n        {\n          \"indexed\": false,\n          \"name\": \"custom_contract\",\n          \"type\": \"address\"\n        }\n      ],\n      \"name\": \"InvokeCustomPreHook\",\n      \"type\": \"event\"\n    },\n    {\n      \"anonymous\": false,\n      \"inputs\": [\n        {\n          \"indexed\": false,\n          \"name\": \"custom_contract\",\n          \"type\": \"address\"\n        },\n        {\n          \"indexed\": false,\n          \"name\": \"result\",\n          \"type\": \"uint256\"\n        }\n      ],\n      \"name\": \"ReturnCustomHook\",\n      \"type\": \"event\"\n    },\n    {\n      \"anonymous\": false,\n      \"inputs\": [\n        {\n          \"indexed\": false,\n          \"name\": \"custom_contract\",\n          \"type\": \"address\"\n        }\n      ],\n      \"name\": \"InvokeCustomPostHook\",\n      \"type\": \"event\"\n    },\n    {\n      \"anonymous\": false,\n      \"inputs\": [\n        {\n          \"indexed\": false,\n          \"name\": \"objectHash\",\n          \"type\": \"bytes32\"\n        }\n      ],\n      \"name\": \"Commit\",\n      \"type\": \"event\"\n    },\n    {\n      \"anonymous\": false,\n      \"inputs\": [\n        {\n          \"indexed\": false,\n          \"name\": \"objectHash\",\n          \"type\": \"bytes32\"\n        }\n      ],\n      \"name\": \"UpdateRequest\",\n      \"type\": \"event\"\n    }\n  ],\n  \"event\": {\n    \"to\": \"0x486Ad523fE847175fFBE5cF2499EA8aAEee8bfc4\",\n    \"from\": \"0xf7C6072c6d61305000E33fF8D8735b3C6af7e10D\",\n    \"contractAddress\": null,\n    \"transactionIndex\": 0,\n    \"root\": \"0xfe353d3772d622d9b895648642922fa21534695150d0e55b9f482e67f6636a2d\",\n    \"gasUsed\": {\n      \"_hex\": \"0x16e54\"\n    },\n    \"logsBloom\": \"0x00000000000000000000000000000000000000000000000000000000000000000000000000000000000000000000000100000000000000000000000000000000000000000000000004000000000000000000000000000000000000000000000000400000000000000000000000000000000000000008000000000000000000000000000000000000000000000000000000000000000000000000000000000000000000000000000000000000000000000000000000000000000000000000000000020000000000000000000000000000000000000000000000000000000000000000000000000000000000000000000000000000000000000000002000000000\",\n    \"blockHash\": \"0x0a03d22bff1ce6fde14d0e96d17ba2a876e3f5ee9d720434073d5da221cd0c4a\",\n    \"transactionHash\": \"0x61def320e033a14a746b4eb4d571f45e917aca683b6225bc2712301f9b234d82\",\n    \"logs\": [\n      {\n        \"transactionIndex\": 0,\n        \"blockNumber\": 67237,\n        \"transactionHash\": \"0x61def320e033a14a746b4eb4d571f45e917aca683b6225bc2712301f9b234d82\",\n        \"address\": \"0x486Ad523fE847175fFBE5cF2499EA8aAEee8bfc4\",\n        \"topics\": [\n          \"0x089a6f1788a3c353423e1be4ba12533bdde7d908bb41abeee185af0acb3df562\"\n        ],\n        \"data\": \"0x00000000000000000000000000000000000000000000000000000000000000010000000000000000000000000000000000000000000000000000000000000000000000000000000000000000000000000000000000000000000000000000000000000000000000000000000000000000000000000000000000000000000000a000000000000000000000000000000000000000000000000000000000000001600000000000000000000000000000000000000000000000000000000000000084307830343036343864643165323761396261336131393937323766343864323765373139363363303465356164363334386337383864626635346236373733663933396437663933396437343932616163613137613731646233393630376664333436383561306639353564353234353961323130386533376364663030373834616532000000000000000000000000000000000000000000000000000000000000000000000000000000000000000000000000000000000000000000000000\",\n        \"logIndex\": 0,\n        \"blockHash\": \"0x0a03d22bff1ce6fde14d0e96d17ba2a876e3f5ee9d720434073d5da221cd0c4a\",\n        \"transactionLogIndex\": 0,\n        \"name\": \"AccessRequest\",\n        \"signature\": \"AccessRequest(uint256,uint8,bytes32,string,string)\",\n        \"topic\": \"0x089a6f1788a3c353423e1be4ba12533bdde7d908bb41abeee185af0acb3df562\",\n        \"values\": {\n          \"0\": {\n            \"_hex\": \"0x01\"\n          },\n          \"1\": 0,\n          \"2\": \"0x0000000000000000000000000000000000000000000000000000000000000000\",\n          \"3\": \"0x040648dd1e27a9ba3a199727f48d27e71963c04e5ad6348c788dbf54b6773f939d7f939d7492aaca17a71db39607fd34685a0f955d52459a2108e37cdf00784ae2\",\n          \"4\": \"\",\n          \"requestID\": {\n            \"_hex\": \"0x01\"\n          },\n          \"level\": 0,\n          \"contentHash\": \"0x0000000000000000000000000000000000000000000000000000000000000000\",\n          \"pkeRequestor\": \"0x040648dd1e27a9ba3a199727f48d27e71963c04e5ad6348c788dbf54b6773f939d7f939d7492aaca17a71db39607fd34685a0f955d52459a2108e37cdf00784ae2\",\n          \"pkeAFGH\": \"\",\n          \"length\": 5\n        }\n      }\n    ],\n    \"blockNumber\": 67237,\n    \"confirmations\": 1,\n    \"cumulativeGasUsed\": {\n      \"_hex\": \"0x16e54\"\n    }\n  },\n  \"eventName\": \"AccessRequest\"\n});",
    "result": {
      "name": "AccessRequest",
      "signature": "AccessRequest(uint256,uint8,bytes32,string,string)",
      "topic": "0x089a6f1788a3c353423e1be4ba12533bdde7d908bb41abeee185af0acb3df562",
      "values": {
        "0": {
          "_hex": "0x01"
        },
        "1": 0,
        "2": "0x0000000000000000000000000000000000000000000000000000000000000000",
        "3": "0x040648dd1e27a9ba3a199727f48d27e71963c04e5ad6348c788dbf54b6773f939d7f939d7492aaca17a71db39607fd34685a0f955d52459a2108e37cdf00784ae2",
        "4": "",
        "requestID": {
          "_hex": "0x01"
        },
        "level": 0,
        "contentHash": "0x0000000000000000000000000000000000000000000000000000000000000000",
        "pkeRequestor": "0x040648dd1e27a9ba3a199727f48d27e71963c04e5ad6348c788dbf54b6773f939d7f939d7492aaca17a71db39607fd34685a0f955d52459a2108e37cdf00784ae2",
        "pkeAFGH": "",
        "length": 5
      }
    }
  },
  {
    "signature": "async ExtractEventFromLogs({\n  \"abi\": [\n    {\n      \"constant\": true,\n      \"inputs\": [],\n      \"name\": \"STATUS_PUBLISHED\",\n      \"outputs\": [\n        {\n          \"name\": \"\",\n          \"type\": \"bytes32\"\n        }\n      ],\n      \"payable\": false,\n      \"stateMutability\": \"view\",\n      \"type\": \"function\"\n    },\n    {\n      \"constant\": true,\n      \"inputs\": [],\n      \"name\": \"creator\",\n      \"outputs\": [\n        {\n          \"name\": \"\",\n          \"type\": \"address\"\n        }\n      ],\n      \"payable\": false,\n      \"stateMutability\": \"view\",\n      \"type\": \"function\"\n    },\n    {\n      \"constant\": false,\n      \"inputs\": [],\n      \"name\": \"publish\",\n      \"outputs\": [\n        {\n          \"name\": \"\",\n          \"type\": \"bool\"\n        }\n      ],\n      \"payable\": true,\n      \"stateMutability\": \"payable\",\n      \"type\": \"function\"\n    },\n    {\n      \"constant\": true,\n      \"inputs\": [\n        {\n          \"name\": \"\",\n          \"type\": \"uint256\"\n        }\n      ],\n      \"name\": \"requestMap\",\n      \"outputs\": [\n        {\n          \"name\": \"originator\",\n          \"type\": \"address\"\n        },\n        {\n          \"name\": \"amountPaid\",\n          \"type\": \"uint256\"\n        },\n        {\n          \"name\": \"status\",\n          \"type\": \"int8\"\n        }\n      ],\n      \"payable\": false,\n      \"stateMutability\": \"view\",\n      \"type\": \"function\"\n    },\n    {\n      \"constant\": true,\n      \"inputs\": [],\n      \"name\": \"contentContractAddress\",\n      \"outputs\": [\n        {\n          \"name\": \"\",\n          \"type\": \"address\"\n        }\n      ],\n      \"payable\": false,\n      \"stateMutability\": \"view\",\n      \"type\": \"function\"\n    },\n    {\n      \"constant\": true,\n      \"inputs\": [],\n      \"name\": \"statusCode\",\n      \"outputs\": [\n        {\n          \"name\": \"\",\n          \"type\": \"int256\"\n        }\n      ],\n      \"payable\": false,\n      \"stateMutability\": \"view\",\n      \"type\": \"function\"\n    },\n    {\n      \"constant\": true,\n      \"inputs\": [],\n      \"name\": \"addressKMS\",\n      \"outputs\": [\n        {\n          \"name\": \"\",\n          \"type\": \"address\"\n        }\n      ],\n      \"payable\": false,\n      \"stateMutability\": \"view\",\n      \"type\": \"function\"\n    },\n    {\n      \"constant\": true,\n      \"inputs\": [],\n      \"name\": \"contentType\",\n      \"outputs\": [\n        {\n          \"name\": \"\",\n          \"type\": \"address\"\n        }\n      ],\n      \"payable\": false,\n      \"stateMutability\": \"view\",\n      \"type\": \"function\"\n    },\n    {\n      \"constant\": true,\n      \"inputs\": [\n        {\n          \"name\": \"status_code\",\n          \"type\": \"int256\"\n        }\n      ],\n      \"name\": \"statusCodeDescription\",\n      \"outputs\": [\n        {\n          \"name\": \"\",\n          \"type\": \"bytes32\"\n        }\n      ],\n      \"payable\": false,\n      \"stateMutability\": \"view\",\n      \"type\": \"function\"\n    },\n    {\n      \"constant\": false,\n      \"inputs\": [],\n      \"name\": \"kill\",\n      \"outputs\": [],\n      \"payable\": false,\n      \"stateMutability\": \"nonpayable\",\n      \"type\": \"function\"\n    },\n    {\n      \"constant\": true,\n      \"inputs\": [],\n      \"name\": \"STATUS_DRAFT\",\n      \"outputs\": [\n        {\n          \"name\": \"\",\n          \"type\": \"bytes32\"\n        }\n      ],\n      \"payable\": false,\n      \"stateMutability\": \"view\",\n      \"type\": \"function\"\n    },\n    {\n      \"constant\": false,\n      \"inputs\": [\n        {\n          \"name\": \"status_code\",\n          \"type\": \"int256\"\n        }\n      ],\n      \"name\": \"setStatusCode\",\n      \"outputs\": [\n        {\n          \"name\": \"\",\n          \"type\": \"int256\"\n        }\n      ],\n      \"payable\": false,\n      \"stateMutability\": \"nonpayable\",\n      \"type\": \"function\"\n    },\n    {\n      \"constant\": false,\n      \"inputs\": [\n        {\n          \"name\": \"request_ID\",\n          \"type\": \"uint256\"\n        },\n        {\n          \"name\": \"score_pct\",\n          \"type\": \"uint256\"\n        },\n        {\n          \"name\": \"ml_out_hash\",\n          \"type\": \"bytes32\"\n        }\n      ],\n      \"name\": \"accessComplete\",\n      \"outputs\": [\n        {\n          \"name\": \"\",\n          \"type\": \"bool\"\n        }\n      ],\n      \"payable\": true,\n      \"stateMutability\": \"payable\",\n      \"type\": \"function\"\n    },\n    {\n      \"constant\": true,\n      \"inputs\": [],\n      \"name\": \"accessCharge\",\n      \"outputs\": [\n        {\n          \"name\": \"\",\n          \"type\": \"uint256\"\n        }\n      ],\n      \"payable\": false,\n      \"stateMutability\": \"view\",\n      \"type\": \"function\"\n    },\n    {\n      \"constant\": false,\n      \"inputs\": [\n        {\n          \"name\": \"newCreator\",\n          \"type\": \"address\"\n        }\n      ],\n      \"name\": \"transferCreatorship\",\n      \"outputs\": [],\n      \"payable\": false,\n      \"stateMutability\": \"nonpayable\",\n      \"type\": \"function\"\n    },\n    {\n      \"constant\": false,\n      \"inputs\": [\n        {\n          \"name\": \"status_code\",\n          \"type\": \"int256\"\n        }\n      ],\n      \"name\": \"updateStatus\",\n      \"outputs\": [\n        {\n          \"name\": \"\",\n          \"type\": \"int256\"\n        }\n      ],\n      \"payable\": false,\n      \"stateMutability\": \"nonpayable\",\n      \"type\": \"function\"\n    },\n    {\n      \"constant\": false,\n      \"inputs\": [\n        {\n          \"name\": \"level\",\n          \"type\": \"uint8\"\n        },\n        {\n          \"name\": \"custom_values\",\n          \"type\": \"bytes32[]\"\n        },\n        {\n          \"name\": \"stakeholders\",\n          \"type\": \"address[]\"\n        }\n      ],\n      \"name\": \"getAccessCharge\",\n      \"outputs\": [\n        {\n          \"name\": \"\",\n          \"type\": \"uint256\"\n        }\n      ],\n      \"payable\": false,\n      \"stateMutability\": \"nonpayable\",\n      \"type\": \"function\"\n    },\n    {\n      \"constant\": true,\n      \"inputs\": [],\n      \"name\": \"owner\",\n      \"outputs\": [\n        {\n          \"name\": \"\",\n          \"type\": \"address\"\n        }\n      ],\n      \"payable\": false,\n      \"stateMutability\": \"view\",\n      \"type\": \"function\"\n    },\n    {\n      \"constant\": true,\n      \"inputs\": [],\n      \"name\": \"requestID\",\n      \"outputs\": [\n        {\n          \"name\": \"\",\n          \"type\": \"uint256\"\n        }\n      ],\n      \"payable\": false,\n      \"stateMutability\": \"view\",\n      \"type\": \"function\"\n    },\n    {\n      \"constant\": false,\n      \"inputs\": [\n        {\n          \"name\": \"level\",\n          \"type\": \"uint8\"\n        },\n        {\n          \"name\": \"pke_requestor\",\n          \"type\": \"string\"\n        },\n        {\n          \"name\": \"pke_AFGH\",\n          \"type\": \"string\"\n        },\n        {\n          \"name\": \"custom_values\",\n          \"type\": \"bytes32[]\"\n        },\n        {\n          \"name\": \"stakeholders\",\n          \"type\": \"address[]\"\n        }\n      ],\n      \"name\": \"accessRequest\",\n      \"outputs\": [\n        {\n          \"name\": \"\",\n          \"type\": \"bool\"\n        }\n      ],\n      \"payable\": true,\n      \"stateMutability\": \"payable\",\n      \"type\": \"function\"\n    },\n    {\n      \"constant\": true,\n      \"inputs\": [],\n      \"name\": \"libraryAddress\",\n      \"outputs\": [\n        {\n          \"name\": \"\",\n          \"type\": \"address\"\n        }\n      ],\n      \"payable\": false,\n      \"stateMutability\": \"view\",\n      \"type\": \"function\"\n    },\n    {\n      \"constant\": false,\n      \"inputs\": [],\n      \"name\": \"updateRequest\",\n      \"outputs\": [],\n      \"payable\": false,\n      \"stateMutability\": \"nonpayable\",\n      \"type\": \"function\"\n    },\n    {\n      \"constant\": false,\n      \"inputs\": [\n        {\n          \"name\": \"address_KMS\",\n          \"type\": \"address\"\n        }\n      ],\n      \"name\": \"setAddressKMS\",\n      \"outputs\": [],\n      \"payable\": false,\n      \"stateMutability\": \"nonpayable\",\n      \"type\": \"function\"\n    },\n    {\n      \"constant\": true,\n      \"inputs\": [],\n      \"name\": \"STATUS_REVIEW\",\n      \"outputs\": [\n        {\n          \"name\": \"\",\n          \"type\": \"bytes32\"\n        }\n      ],\n      \"payable\": false,\n      \"stateMutability\": \"view\",\n      \"type\": \"function\"\n    },\n    {\n      \"constant\": true,\n      \"inputs\": [],\n      \"name\": \"objectHash\",\n      \"outputs\": [\n        {\n          \"name\": \"\",\n          \"type\": \"bytes32\"\n        }\n      ],\n      \"payable\": false,\n      \"stateMutability\": \"view\",\n      \"type\": \"function\"\n    },\n    {\n      \"constant\": false,\n      \"inputs\": [\n        {\n          \"name\": \"addr\",\n          \"type\": \"address\"\n        }\n      ],\n      \"name\": \"setContentContractAddress\",\n      \"outputs\": [],\n      \"payable\": false,\n      \"stateMutability\": \"nonpayable\",\n      \"type\": \"function\"\n    },\n    {\n      \"constant\": false,\n      \"inputs\": [\n        {\n          \"name\": \"request_ID\",\n          \"type\": \"uint256\"\n        },\n        {\n          \"name\": \"access_granted\",\n          \"type\": \"bool\"\n        },\n        {\n          \"name\": \"re_key\",\n          \"type\": \"string\"\n        },\n        {\n          \"name\": \"encrypted_AES_key\",\n          \"type\": \"string\"\n        }\n      ],\n      \"name\": \"accessGrant\",\n      \"outputs\": [\n        {\n          \"name\": \"\",\n          \"type\": \"bool\"\n        }\n      ],\n      \"payable\": false,\n      \"stateMutability\": \"nonpayable\",\n      \"type\": \"function\"\n    },\n    {\n      \"constant\": false,\n      \"inputs\": [\n        {\n          \"name\": \"object_hash\",\n          \"type\": \"bytes32\"\n        }\n      ],\n      \"name\": \"commit\",\n      \"outputs\": [],\n      \"payable\": false,\n      \"stateMutability\": \"nonpayable\",\n      \"type\": \"function\"\n    },\n    {\n      \"constant\": false,\n      \"inputs\": [\n        {\n          \"name\": \"newOwner\",\n          \"type\": \"address\"\n        }\n      ],\n      \"name\": \"transferOwnership\",\n      \"outputs\": [],\n      \"payable\": false,\n      \"stateMutability\": \"nonpayable\",\n      \"type\": \"function\"\n    },\n    {\n      \"constant\": false,\n      \"inputs\": [\n        {\n          \"name\": \"charge\",\n          \"type\": \"uint256\"\n        }\n      ],\n      \"name\": \"setAccessCharge\",\n      \"outputs\": [\n        {\n          \"name\": \"\",\n          \"type\": \"uint256\"\n        }\n      ],\n      \"payable\": false,\n      \"stateMutability\": \"nonpayable\",\n      \"type\": \"function\"\n    },\n    {\n      \"constant\": true,\n      \"inputs\": [],\n      \"name\": \"statusDescription\",\n      \"outputs\": [\n        {\n          \"name\": \"\",\n          \"type\": \"bytes32\"\n        }\n      ],\n      \"payable\": false,\n      \"stateMutability\": \"view\",\n      \"type\": \"function\"\n    },\n    {\n      \"inputs\": [\n        {\n          \"name\": \"content_type\",\n          \"type\": \"address\"\n        }\n      ],\n      \"payable\": true,\n      \"stateMutability\": \"payable\",\n      \"type\": \"constructor\"\n    },\n    {\n      \"payable\": true,\n      \"stateMutability\": \"payable\",\n      \"type\": \"fallback\"\n    },\n    {\n      \"anonymous\": false,\n      \"inputs\": [\n        {\n          \"indexed\": false,\n          \"name\": \"containingLibrary\",\n          \"type\": \"address\"\n        }\n      ],\n      \"name\": \"ContentObjectCreate\",\n      \"type\": \"event\"\n    },\n    {\n      \"anonymous\": false,\n      \"inputs\": [\n        {\n          \"indexed\": false,\n          \"name\": \"contentType\",\n          \"type\": \"address\"\n        },\n        {\n          \"indexed\": false,\n          \"name\": \"contentContractAddress\",\n          \"type\": \"address\"\n        }\n      ],\n      \"name\": \"SetContentType\",\n      \"type\": \"event\"\n    },\n    {\n      \"anonymous\": false,\n      \"inputs\": [\n        {\n          \"indexed\": false,\n          \"name\": \"requestID\",\n          \"type\": \"uint256\"\n        },\n        {\n          \"indexed\": false,\n          \"name\": \"level\",\n          \"type\": \"uint8\"\n        },\n        {\n          \"indexed\": false,\n          \"name\": \"contentHash\",\n          \"type\": \"bytes32\"\n        },\n        {\n          \"indexed\": false,\n          \"name\": \"pkeRequestor\",\n          \"type\": \"string\"\n        },\n        {\n          \"indexed\": false,\n          \"name\": \"pkeAFGH\",\n          \"type\": \"string\"\n        }\n      ],\n      \"name\": \"AccessRequest\",\n      \"type\": \"event\"\n    },\n    {\n      \"anonymous\": false,\n      \"inputs\": [\n        {\n          \"indexed\": false,\n          \"name\": \"requestID\",\n          \"type\": \"uint256\"\n        },\n        {\n          \"indexed\": false,\n          \"name\": \"access_granted\",\n          \"type\": \"bool\"\n        },\n        {\n          \"indexed\": false,\n          \"name\": \"reKey\",\n          \"type\": \"string\"\n        },\n        {\n          \"indexed\": false,\n          \"name\": \"encryptedAESKey\",\n          \"type\": \"string\"\n        }\n      ],\n      \"name\": \"AccessGrant\",\n      \"type\": \"event\"\n    },\n    {\n      \"anonymous\": false,\n      \"inputs\": [\n        {\n          \"indexed\": false,\n          \"name\": \"customValue\",\n          \"type\": \"bytes32\"\n        }\n      ],\n      \"name\": \"AccessRequestValue\",\n      \"type\": \"event\"\n    },\n    {\n      \"anonymous\": false,\n      \"inputs\": [\n        {\n          \"indexed\": false,\n          \"name\": \"stakeholder\",\n          \"type\": \"address\"\n        }\n      ],\n      \"name\": \"AccessRequestStakeholder\",\n      \"type\": \"event\"\n    },\n    {\n      \"anonymous\": false,\n      \"inputs\": [\n        {\n          \"indexed\": false,\n          \"name\": \"requestID\",\n          \"type\": \"uint256\"\n        },\n        {\n          \"indexed\": false,\n          \"name\": \"scorePct\",\n          \"type\": \"uint256\"\n        },\n        {\n          \"indexed\": false,\n          \"name\": \"mlOutHash\",\n          \"type\": \"bytes32\"\n        },\n        {\n          \"indexed\": false,\n          \"name\": \"customContractResult\",\n          \"type\": \"bool\"\n        }\n      ],\n      \"name\": \"AccessComplete\",\n      \"type\": \"event\"\n    },\n    {\n      \"anonymous\": false,\n      \"inputs\": [\n        {\n          \"indexed\": false,\n          \"name\": \"contentContractAddress\",\n          \"type\": \"address\"\n        }\n      ],\n      \"name\": \"SetContentContract\",\n      \"type\": \"event\"\n    },\n    {\n      \"anonymous\": false,\n      \"inputs\": [\n        {\n          \"indexed\": false,\n          \"name\": \"accessCharge\",\n          \"type\": \"uint256\"\n        }\n      ],\n      \"name\": \"SetAccessCharge\",\n      \"type\": \"event\"\n    },\n    {\n      \"anonymous\": false,\n      \"inputs\": [\n        {\n          \"indexed\": false,\n          \"name\": \"level\",\n          \"type\": \"uint8\"\n        },\n        {\n          \"indexed\": false,\n          \"name\": \"accessCharge\",\n          \"type\": \"uint256\"\n        }\n      ],\n      \"name\": \"GetAccessCharge\",\n      \"type\": \"event\"\n    },\n    {\n      \"anonymous\": false,\n      \"inputs\": [\n        {\n          \"indexed\": false,\n          \"name\": \"accessCharge\",\n          \"type\": \"uint256\"\n        },\n        {\n          \"indexed\": false,\n          \"name\": \"amountProvided\",\n          \"type\": \"uint256\"\n        }\n      ],\n      \"name\": \"InsufficientFunds\",\n      \"type\": \"event\"\n    },\n    {\n      \"anonymous\": false,\n      \"inputs\": [\n        {\n          \"indexed\": false,\n          \"name\": \"statusCode\",\n          \"type\": \"int256\"\n        }\n      ],\n      \"name\": \"SetStatusCode\",\n      \"type\": \"event\"\n    },\n    {\n      \"anonymous\": false,\n      \"inputs\": [\n        {\n          \"indexed\": false,\n          \"name\": \"requestStatus\",\n          \"type\": \"bool\"\n        },\n        {\n          \"indexed\": false,\n          \"name\": \"statusCode\",\n          \"type\": \"int256\"\n        },\n        {\n          \"indexed\": false,\n          \"name\": \"objectHash\",\n          \"type\": \"bytes32\"\n        }\n      ],\n      \"name\": \"Publish\",\n      \"type\": \"event\"\n    },\n    {\n      \"anonymous\": false,\n      \"inputs\": [\n        {\n          \"indexed\": false,\n          \"name\": \"custom_contract\",\n          \"type\": \"address\"\n        }\n      ],\n      \"name\": \"InvokeCustomPreHook\",\n      \"type\": \"event\"\n    },\n    {\n      \"anonymous\": false,\n      \"inputs\": [\n        {\n          \"indexed\": false,\n          \"name\": \"custom_contract\",\n          \"type\": \"address\"\n        },\n        {\n          \"indexed\": false,\n          \"name\": \"result\",\n          \"type\": \"uint256\"\n        }\n      ],\n      \"name\": \"ReturnCustomHook\",\n      \"type\": \"event\"\n    },\n    {\n      \"anonymous\": false,\n      \"inputs\": [\n        {\n          \"indexed\": false,\n          \"name\": \"custom_contract\",\n          \"type\": \"address\"\n        }\n      ],\n      \"name\": \"InvokeCustomPostHook\",\n      \"type\": \"event\"\n    },\n    {\n      \"anonymous\": false,\n      \"inputs\": [\n        {\n          \"indexed\": false,\n          \"name\": \"objectHash\",\n          \"type\": \"bytes32\"\n        }\n      ],\n      \"name\": \"Commit\",\n      \"type\": \"event\"\n    },\n    {\n      \"anonymous\": false,\n      \"inputs\": [\n        {\n          \"indexed\": false,\n          \"name\": \"objectHash\",\n          \"type\": \"bytes32\"\n        }\n      ],\n      \"name\": \"UpdateRequest\",\n      \"type\": \"event\"\n    }\n  ],\n  \"event\": {\n    \"to\": \"0x3F0AD83d1e0Ae510eb7764B52Ef21be12BEB7d3C\",\n    \"from\": \"0xf7C6072c6d61305000E33fF8D8735b3C6af7e10D\",\n    \"contractAddress\": null,\n    \"transactionIndex\": 0,\n    \"root\": \"0x27dfeca9573b82a450081495e068fc5877090f1534a1b036afad26caa71a2077\",\n    \"gasUsed\": {\n      \"_hex\": \"0x133bc\"\n    },\n    \"logsBloom\": \"0x00000000000000000000000000000000000000000000000000000000000000000000000000000000000000000000000000000000000000000000000000000000000000000000000004000000000000000000000000000000000000000000000000400000000000000000000000000000000000000000000000000000000000000000000000000000000000000200000000000000000000000000000000000000000000000000000000000000000000000000000000000000000000000000000000000000000000000000000000000000000000080000000000000000008000000000000000000000000000000000000000000000000000000000002000000000\",\n    \"blockHash\": \"0xe74743ab0c2927cac5a98ed45de57ec319ac10d03e2092979141908f03206f7f\",\n    \"transactionHash\": \"0xf9439c53209e3cd9fc6fbf93a6eb44ff96efdf8ecccb54a9b70df9247c60050f\",\n    \"logs\": [\n      {\n        \"transactionIndex\": 0,\n        \"blockNumber\": 67238,\n        \"transactionHash\": \"0xf9439c53209e3cd9fc6fbf93a6eb44ff96efdf8ecccb54a9b70df9247c60050f\",\n        \"address\": \"0x3F0AD83d1e0Ae510eb7764B52Ef21be12BEB7d3C\",\n        \"topics\": [\n          \"0x089a6f1788a3c353423e1be4ba12533bdde7d908bb41abeee185af0acb3df562\"\n        ],\n        \"data\": \"0x00000000000000000000000000000000000000000000000000000000000000020000000000000000000000000000000000000000000000000000000000000000000000000000000000000000000000000000000000000000000000000000000000000000000000000000000000000000000000000000000000000000000000a000000000000000000000000000000000000000000000000000000000000001600000000000000000000000000000000000000000000000000000000000000084307830343036343864643165323761396261336131393937323766343864323765373139363363303465356164363334386337383864626635346236373733663933396437663933396437343932616163613137613731646233393630376664333436383561306639353564353234353961323130386533376364663030373834616532000000000000000000000000000000000000000000000000000000000000000000000000000000000000000000000000000000000000000000000000\",\n        \"logIndex\": 0,\n        \"blockHash\": \"0xe74743ab0c2927cac5a98ed45de57ec319ac10d03e2092979141908f03206f7f\",\n        \"transactionLogIndex\": 0,\n        \"name\": \"AccessRequest\",\n        \"signature\": \"AccessRequest(uint256,uint8,bytes32,string,string)\",\n        \"topic\": \"0x089a6f1788a3c353423e1be4ba12533bdde7d908bb41abeee185af0acb3df562\",\n        \"values\": {\n          \"0\": {\n            \"_hex\": \"0x02\"\n          },\n          \"1\": 0,\n          \"2\": \"0x0000000000000000000000000000000000000000000000000000000000000000\",\n          \"3\": \"0x040648dd1e27a9ba3a199727f48d27e71963c04e5ad6348c788dbf54b6773f939d7f939d7492aaca17a71db39607fd34685a0f955d52459a2108e37cdf00784ae2\",\n          \"4\": \"\",\n          \"requestID\": {\n            \"_hex\": \"0x02\"\n          },\n          \"level\": 0,\n          \"contentHash\": \"0x0000000000000000000000000000000000000000000000000000000000000000\",\n          \"pkeRequestor\": \"0x040648dd1e27a9ba3a199727f48d27e71963c04e5ad6348c788dbf54b6773f939d7f939d7492aaca17a71db39607fd34685a0f955d52459a2108e37cdf00784ae2\",\n          \"pkeAFGH\": \"\",\n          \"length\": 5\n        }\n      }\n    ],\n    \"blockNumber\": 67238,\n    \"confirmations\": 1,\n    \"cumulativeGasUsed\": {\n      \"_hex\": \"0x133bc\"\n    }\n  },\n  \"eventName\": \"AccessRequest\"\n});",
    "result": {
      "name": "AccessRequest",
      "signature": "AccessRequest(uint256,uint8,bytes32,string,string)",
      "topic": "0x089a6f1788a3c353423e1be4ba12533bdde7d908bb41abeee185af0acb3df562",
      "values": {
        "0": {
          "_hex": "0x02"
        },
        "1": 0,
        "2": "0x0000000000000000000000000000000000000000000000000000000000000000",
        "3": "0x040648dd1e27a9ba3a199727f48d27e71963c04e5ad6348c788dbf54b6773f939d7f939d7492aaca17a71db39607fd34685a0f955d52459a2108e37cdf00784ae2",
        "4": "",
        "requestID": {
          "_hex": "0x02"
        },
        "level": 0,
        "contentHash": "0x0000000000000000000000000000000000000000000000000000000000000000",
        "pkeRequestor": "0x040648dd1e27a9ba3a199727f48d27e71963c04e5ad6348c788dbf54b6773f939d7f939d7492aaca17a71db39607fd34685a0f955d52459a2108e37cdf00784ae2",
        "pkeAFGH": "",
        "length": 5
      }
    }
  },
  {
    "signature": "async ExtractEventFromLogs({\n  \"abi\": [\n    {\n      \"constant\": true,\n      \"inputs\": [],\n      \"name\": \"STATUS_PUBLISHED\",\n      \"outputs\": [\n        {\n          \"name\": \"\",\n          \"type\": \"bytes32\"\n        }\n      ],\n      \"payable\": false,\n      \"stateMutability\": \"view\",\n      \"type\": \"function\"\n    },\n    {\n      \"constant\": true,\n      \"inputs\": [],\n      \"name\": \"creator\",\n      \"outputs\": [\n        {\n          \"name\": \"\",\n          \"type\": \"address\"\n        }\n      ],\n      \"payable\": false,\n      \"stateMutability\": \"view\",\n      \"type\": \"function\"\n    },\n    {\n      \"constant\": false,\n      \"inputs\": [],\n      \"name\": \"publish\",\n      \"outputs\": [\n        {\n          \"name\": \"\",\n          \"type\": \"bool\"\n        }\n      ],\n      \"payable\": true,\n      \"stateMutability\": \"payable\",\n      \"type\": \"function\"\n    },\n    {\n      \"constant\": true,\n      \"inputs\": [\n        {\n          \"name\": \"\",\n          \"type\": \"uint256\"\n        }\n      ],\n      \"name\": \"requestMap\",\n      \"outputs\": [\n        {\n          \"name\": \"originator\",\n          \"type\": \"address\"\n        },\n        {\n          \"name\": \"amountPaid\",\n          \"type\": \"uint256\"\n        },\n        {\n          \"name\": \"status\",\n          \"type\": \"int8\"\n        }\n      ],\n      \"payable\": false,\n      \"stateMutability\": \"view\",\n      \"type\": \"function\"\n    },\n    {\n      \"constant\": true,\n      \"inputs\": [],\n      \"name\": \"contentContractAddress\",\n      \"outputs\": [\n        {\n          \"name\": \"\",\n          \"type\": \"address\"\n        }\n      ],\n      \"payable\": false,\n      \"stateMutability\": \"view\",\n      \"type\": \"function\"\n    },\n    {\n      \"constant\": true,\n      \"inputs\": [],\n      \"name\": \"statusCode\",\n      \"outputs\": [\n        {\n          \"name\": \"\",\n          \"type\": \"int256\"\n        }\n      ],\n      \"payable\": false,\n      \"stateMutability\": \"view\",\n      \"type\": \"function\"\n    },\n    {\n      \"constant\": true,\n      \"inputs\": [],\n      \"name\": \"addressKMS\",\n      \"outputs\": [\n        {\n          \"name\": \"\",\n          \"type\": \"address\"\n        }\n      ],\n      \"payable\": false,\n      \"stateMutability\": \"view\",\n      \"type\": \"function\"\n    },\n    {\n      \"constant\": true,\n      \"inputs\": [],\n      \"name\": \"contentType\",\n      \"outputs\": [\n        {\n          \"name\": \"\",\n          \"type\": \"address\"\n        }\n      ],\n      \"payable\": false,\n      \"stateMutability\": \"view\",\n      \"type\": \"function\"\n    },\n    {\n      \"constant\": true,\n      \"inputs\": [\n        {\n          \"name\": \"status_code\",\n          \"type\": \"int256\"\n        }\n      ],\n      \"name\": \"statusCodeDescription\",\n      \"outputs\": [\n        {\n          \"name\": \"\",\n          \"type\": \"bytes32\"\n        }\n      ],\n      \"payable\": false,\n      \"stateMutability\": \"view\",\n      \"type\": \"function\"\n    },\n    {\n      \"constant\": false,\n      \"inputs\": [],\n      \"name\": \"kill\",\n      \"outputs\": [],\n      \"payable\": false,\n      \"stateMutability\": \"nonpayable\",\n      \"type\": \"function\"\n    },\n    {\n      \"constant\": true,\n      \"inputs\": [],\n      \"name\": \"STATUS_DRAFT\",\n      \"outputs\": [\n        {\n          \"name\": \"\",\n          \"type\": \"bytes32\"\n        }\n      ],\n      \"payable\": false,\n      \"stateMutability\": \"view\",\n      \"type\": \"function\"\n    },\n    {\n      \"constant\": false,\n      \"inputs\": [\n        {\n          \"name\": \"status_code\",\n          \"type\": \"int256\"\n        }\n      ],\n      \"name\": \"setStatusCode\",\n      \"outputs\": [\n        {\n          \"name\": \"\",\n          \"type\": \"int256\"\n        }\n      ],\n      \"payable\": false,\n      \"stateMutability\": \"nonpayable\",\n      \"type\": \"function\"\n    },\n    {\n      \"constant\": false,\n      \"inputs\": [\n        {\n          \"name\": \"request_ID\",\n          \"type\": \"uint256\"\n        },\n        {\n          \"name\": \"score_pct\",\n          \"type\": \"uint256\"\n        },\n        {\n          \"name\": \"ml_out_hash\",\n          \"type\": \"bytes32\"\n        }\n      ],\n      \"name\": \"accessComplete\",\n      \"outputs\": [\n        {\n          \"name\": \"\",\n          \"type\": \"bool\"\n        }\n      ],\n      \"payable\": true,\n      \"stateMutability\": \"payable\",\n      \"type\": \"function\"\n    },\n    {\n      \"constant\": true,\n      \"inputs\": [],\n      \"name\": \"accessCharge\",\n      \"outputs\": [\n        {\n          \"name\": \"\",\n          \"type\": \"uint256\"\n        }\n      ],\n      \"payable\": false,\n      \"stateMutability\": \"view\",\n      \"type\": \"function\"\n    },\n    {\n      \"constant\": false,\n      \"inputs\": [\n        {\n          \"name\": \"newCreator\",\n          \"type\": \"address\"\n        }\n      ],\n      \"name\": \"transferCreatorship\",\n      \"outputs\": [],\n      \"payable\": false,\n      \"stateMutability\": \"nonpayable\",\n      \"type\": \"function\"\n    },\n    {\n      \"constant\": false,\n      \"inputs\": [\n        {\n          \"name\": \"status_code\",\n          \"type\": \"int256\"\n        }\n      ],\n      \"name\": \"updateStatus\",\n      \"outputs\": [\n        {\n          \"name\": \"\",\n          \"type\": \"int256\"\n        }\n      ],\n      \"payable\": false,\n      \"stateMutability\": \"nonpayable\",\n      \"type\": \"function\"\n    },\n    {\n      \"constant\": false,\n      \"inputs\": [\n        {\n          \"name\": \"level\",\n          \"type\": \"uint8\"\n        },\n        {\n          \"name\": \"custom_values\",\n          \"type\": \"bytes32[]\"\n        },\n        {\n          \"name\": \"stakeholders\",\n          \"type\": \"address[]\"\n        }\n      ],\n      \"name\": \"getAccessCharge\",\n      \"outputs\": [\n        {\n          \"name\": \"\",\n          \"type\": \"uint256\"\n        }\n      ],\n      \"payable\": false,\n      \"stateMutability\": \"nonpayable\",\n      \"type\": \"function\"\n    },\n    {\n      \"constant\": true,\n      \"inputs\": [],\n      \"name\": \"owner\",\n      \"outputs\": [\n        {\n          \"name\": \"\",\n          \"type\": \"address\"\n        }\n      ],\n      \"payable\": false,\n      \"stateMutability\": \"view\",\n      \"type\": \"function\"\n    },\n    {\n      \"constant\": true,\n      \"inputs\": [],\n      \"name\": \"requestID\",\n      \"outputs\": [\n        {\n          \"name\": \"\",\n          \"type\": \"uint256\"\n        }\n      ],\n      \"payable\": false,\n      \"stateMutability\": \"view\",\n      \"type\": \"function\"\n    },\n    {\n      \"constant\": false,\n      \"inputs\": [\n        {\n          \"name\": \"level\",\n          \"type\": \"uint8\"\n        },\n        {\n          \"name\": \"pke_requestor\",\n          \"type\": \"string\"\n        },\n        {\n          \"name\": \"pke_AFGH\",\n          \"type\": \"string\"\n        },\n        {\n          \"name\": \"custom_values\",\n          \"type\": \"bytes32[]\"\n        },\n        {\n          \"name\": \"stakeholders\",\n          \"type\": \"address[]\"\n        }\n      ],\n      \"name\": \"accessRequest\",\n      \"outputs\": [\n        {\n          \"name\": \"\",\n          \"type\": \"bool\"\n        }\n      ],\n      \"payable\": true,\n      \"stateMutability\": \"payable\",\n      \"type\": \"function\"\n    },\n    {\n      \"constant\": true,\n      \"inputs\": [],\n      \"name\": \"libraryAddress\",\n      \"outputs\": [\n        {\n          \"name\": \"\",\n          \"type\": \"address\"\n        }\n      ],\n      \"payable\": false,\n      \"stateMutability\": \"view\",\n      \"type\": \"function\"\n    },\n    {\n      \"constant\": false,\n      \"inputs\": [],\n      \"name\": \"updateRequest\",\n      \"outputs\": [],\n      \"payable\": false,\n      \"stateMutability\": \"nonpayable\",\n      \"type\": \"function\"\n    },\n    {\n      \"constant\": false,\n      \"inputs\": [\n        {\n          \"name\": \"address_KMS\",\n          \"type\": \"address\"\n        }\n      ],\n      \"name\": \"setAddressKMS\",\n      \"outputs\": [],\n      \"payable\": false,\n      \"stateMutability\": \"nonpayable\",\n      \"type\": \"function\"\n    },\n    {\n      \"constant\": true,\n      \"inputs\": [],\n      \"name\": \"STATUS_REVIEW\",\n      \"outputs\": [\n        {\n          \"name\": \"\",\n          \"type\": \"bytes32\"\n        }\n      ],\n      \"payable\": false,\n      \"stateMutability\": \"view\",\n      \"type\": \"function\"\n    },\n    {\n      \"constant\": true,\n      \"inputs\": [],\n      \"name\": \"objectHash\",\n      \"outputs\": [\n        {\n          \"name\": \"\",\n          \"type\": \"bytes32\"\n        }\n      ],\n      \"payable\": false,\n      \"stateMutability\": \"view\",\n      \"type\": \"function\"\n    },\n    {\n      \"constant\": false,\n      \"inputs\": [\n        {\n          \"name\": \"addr\",\n          \"type\": \"address\"\n        }\n      ],\n      \"name\": \"setContentContractAddress\",\n      \"outputs\": [],\n      \"payable\": false,\n      \"stateMutability\": \"nonpayable\",\n      \"type\": \"function\"\n    },\n    {\n      \"constant\": false,\n      \"inputs\": [\n        {\n          \"name\": \"request_ID\",\n          \"type\": \"uint256\"\n        },\n        {\n          \"name\": \"access_granted\",\n          \"type\": \"bool\"\n        },\n        {\n          \"name\": \"re_key\",\n          \"type\": \"string\"\n        },\n        {\n          \"name\": \"encrypted_AES_key\",\n          \"type\": \"string\"\n        }\n      ],\n      \"name\": \"accessGrant\",\n      \"outputs\": [\n        {\n          \"name\": \"\",\n          \"type\": \"bool\"\n        }\n      ],\n      \"payable\": false,\n      \"stateMutability\": \"nonpayable\",\n      \"type\": \"function\"\n    },\n    {\n      \"constant\": false,\n      \"inputs\": [\n        {\n          \"name\": \"object_hash\",\n          \"type\": \"bytes32\"\n        }\n      ],\n      \"name\": \"commit\",\n      \"outputs\": [],\n      \"payable\": false,\n      \"stateMutability\": \"nonpayable\",\n      \"type\": \"function\"\n    },\n    {\n      \"constant\": false,\n      \"inputs\": [\n        {\n          \"name\": \"newOwner\",\n          \"type\": \"address\"\n        }\n      ],\n      \"name\": \"transferOwnership\",\n      \"outputs\": [],\n      \"payable\": false,\n      \"stateMutability\": \"nonpayable\",\n      \"type\": \"function\"\n    },\n    {\n      \"constant\": false,\n      \"inputs\": [\n        {\n          \"name\": \"charge\",\n          \"type\": \"uint256\"\n        }\n      ],\n      \"name\": \"setAccessCharge\",\n      \"outputs\": [\n        {\n          \"name\": \"\",\n          \"type\": \"uint256\"\n        }\n      ],\n      \"payable\": false,\n      \"stateMutability\": \"nonpayable\",\n      \"type\": \"function\"\n    },\n    {\n      \"constant\": true,\n      \"inputs\": [],\n      \"name\": \"statusDescription\",\n      \"outputs\": [\n        {\n          \"name\": \"\",\n          \"type\": \"bytes32\"\n        }\n      ],\n      \"payable\": false,\n      \"stateMutability\": \"view\",\n      \"type\": \"function\"\n    },\n    {\n      \"inputs\": [\n        {\n          \"name\": \"content_type\",\n          \"type\": \"address\"\n        }\n      ],\n      \"payable\": true,\n      \"stateMutability\": \"payable\",\n      \"type\": \"constructor\"\n    },\n    {\n      \"payable\": true,\n      \"stateMutability\": \"payable\",\n      \"type\": \"fallback\"\n    },\n    {\n      \"anonymous\": false,\n      \"inputs\": [\n        {\n          \"indexed\": false,\n          \"name\": \"containingLibrary\",\n          \"type\": \"address\"\n        }\n      ],\n      \"name\": \"ContentObjectCreate\",\n      \"type\": \"event\"\n    },\n    {\n      \"anonymous\": false,\n      \"inputs\": [\n        {\n          \"indexed\": false,\n          \"name\": \"contentType\",\n          \"type\": \"address\"\n        },\n        {\n          \"indexed\": false,\n          \"name\": \"contentContractAddress\",\n          \"type\": \"address\"\n        }\n      ],\n      \"name\": \"SetContentType\",\n      \"type\": \"event\"\n    },\n    {\n      \"anonymous\": false,\n      \"inputs\": [\n        {\n          \"indexed\": false,\n          \"name\": \"requestID\",\n          \"type\": \"uint256\"\n        },\n        {\n          \"indexed\": false,\n          \"name\": \"level\",\n          \"type\": \"uint8\"\n        },\n        {\n          \"indexed\": false,\n          \"name\": \"contentHash\",\n          \"type\": \"bytes32\"\n        },\n        {\n          \"indexed\": false,\n          \"name\": \"pkeRequestor\",\n          \"type\": \"string\"\n        },\n        {\n          \"indexed\": false,\n          \"name\": \"pkeAFGH\",\n          \"type\": \"string\"\n        }\n      ],\n      \"name\": \"AccessRequest\",\n      \"type\": \"event\"\n    },\n    {\n      \"anonymous\": false,\n      \"inputs\": [\n        {\n          \"indexed\": false,\n          \"name\": \"requestID\",\n          \"type\": \"uint256\"\n        },\n        {\n          \"indexed\": false,\n          \"name\": \"access_granted\",\n          \"type\": \"bool\"\n        },\n        {\n          \"indexed\": false,\n          \"name\": \"reKey\",\n          \"type\": \"string\"\n        },\n        {\n          \"indexed\": false,\n          \"name\": \"encryptedAESKey\",\n          \"type\": \"string\"\n        }\n      ],\n      \"name\": \"AccessGrant\",\n      \"type\": \"event\"\n    },\n    {\n      \"anonymous\": false,\n      \"inputs\": [\n        {\n          \"indexed\": false,\n          \"name\": \"customValue\",\n          \"type\": \"bytes32\"\n        }\n      ],\n      \"name\": \"AccessRequestValue\",\n      \"type\": \"event\"\n    },\n    {\n      \"anonymous\": false,\n      \"inputs\": [\n        {\n          \"indexed\": false,\n          \"name\": \"stakeholder\",\n          \"type\": \"address\"\n        }\n      ],\n      \"name\": \"AccessRequestStakeholder\",\n      \"type\": \"event\"\n    },\n    {\n      \"anonymous\": false,\n      \"inputs\": [\n        {\n          \"indexed\": false,\n          \"name\": \"requestID\",\n          \"type\": \"uint256\"\n        },\n        {\n          \"indexed\": false,\n          \"name\": \"scorePct\",\n          \"type\": \"uint256\"\n        },\n        {\n          \"indexed\": false,\n          \"name\": \"mlOutHash\",\n          \"type\": \"bytes32\"\n        },\n        {\n          \"indexed\": false,\n          \"name\": \"customContractResult\",\n          \"type\": \"bool\"\n        }\n      ],\n      \"name\": \"AccessComplete\",\n      \"type\": \"event\"\n    },\n    {\n      \"anonymous\": false,\n      \"inputs\": [\n        {\n          \"indexed\": false,\n          \"name\": \"contentContractAddress\",\n          \"type\": \"address\"\n        }\n      ],\n      \"name\": \"SetContentContract\",\n      \"type\": \"event\"\n    },\n    {\n      \"anonymous\": false,\n      \"inputs\": [\n        {\n          \"indexed\": false,\n          \"name\": \"accessCharge\",\n          \"type\": \"uint256\"\n        }\n      ],\n      \"name\": \"SetAccessCharge\",\n      \"type\": \"event\"\n    },\n    {\n      \"anonymous\": false,\n      \"inputs\": [\n        {\n          \"indexed\": false,\n          \"name\": \"level\",\n          \"type\": \"uint8\"\n        },\n        {\n          \"indexed\": false,\n          \"name\": \"accessCharge\",\n          \"type\": \"uint256\"\n        }\n      ],\n      \"name\": \"GetAccessCharge\",\n      \"type\": \"event\"\n    },\n    {\n      \"anonymous\": false,\n      \"inputs\": [\n        {\n          \"indexed\": false,\n          \"name\": \"accessCharge\",\n          \"type\": \"uint256\"\n        },\n        {\n          \"indexed\": false,\n          \"name\": \"amountProvided\",\n          \"type\": \"uint256\"\n        }\n      ],\n      \"name\": \"InsufficientFunds\",\n      \"type\": \"event\"\n    },\n    {\n      \"anonymous\": false,\n      \"inputs\": [\n        {\n          \"indexed\": false,\n          \"name\": \"statusCode\",\n          \"type\": \"int256\"\n        }\n      ],\n      \"name\": \"SetStatusCode\",\n      \"type\": \"event\"\n    },\n    {\n      \"anonymous\": false,\n      \"inputs\": [\n        {\n          \"indexed\": false,\n          \"name\": \"requestStatus\",\n          \"type\": \"bool\"\n        },\n        {\n          \"indexed\": false,\n          \"name\": \"statusCode\",\n          \"type\": \"int256\"\n        },\n        {\n          \"indexed\": false,\n          \"name\": \"objectHash\",\n          \"type\": \"bytes32\"\n        }\n      ],\n      \"name\": \"Publish\",\n      \"type\": \"event\"\n    },\n    {\n      \"anonymous\": false,\n      \"inputs\": [\n        {\n          \"indexed\": false,\n          \"name\": \"custom_contract\",\n          \"type\": \"address\"\n        }\n      ],\n      \"name\": \"InvokeCustomPreHook\",\n      \"type\": \"event\"\n    },\n    {\n      \"anonymous\": false,\n      \"inputs\": [\n        {\n          \"indexed\": false,\n          \"name\": \"custom_contract\",\n          \"type\": \"address\"\n        },\n        {\n          \"indexed\": false,\n          \"name\": \"result\",\n          \"type\": \"uint256\"\n        }\n      ],\n      \"name\": \"ReturnCustomHook\",\n      \"type\": \"event\"\n    },\n    {\n      \"anonymous\": false,\n      \"inputs\": [\n        {\n          \"indexed\": false,\n          \"name\": \"custom_contract\",\n          \"type\": \"address\"\n        }\n      ],\n      \"name\": \"InvokeCustomPostHook\",\n      \"type\": \"event\"\n    },\n    {\n      \"anonymous\": false,\n      \"inputs\": [\n        {\n          \"indexed\": false,\n          \"name\": \"objectHash\",\n          \"type\": \"bytes32\"\n        }\n      ],\n      \"name\": \"Commit\",\n      \"type\": \"event\"\n    },\n    {\n      \"anonymous\": false,\n      \"inputs\": [\n        {\n          \"indexed\": false,\n          \"name\": \"objectHash\",\n          \"type\": \"bytes32\"\n        }\n      ],\n      \"name\": \"UpdateRequest\",\n      \"type\": \"event\"\n    }\n  ],\n  \"event\": {\n    \"to\": \"0x3F0AD83d1e0Ae510eb7764B52Ef21be12BEB7d3C\",\n    \"from\": \"0xf7C6072c6d61305000E33fF8D8735b3C6af7e10D\",\n    \"contractAddress\": null,\n    \"transactionIndex\": 0,\n    \"root\": \"0xceb8572525a52041b766fc9d22ea49f1fc7d11a56e5d2074b09d135ec96df941\",\n    \"gasUsed\": {\n      \"_hex\": \"0x1837a\"\n    },\n    \"logsBloom\": \"0x00000000040000000000000000000000000000000000000000000000000000000000080000000000000000000000000000000000000000000000000000000000000000000000000000000000000000000000000000000000000000000000000000000000000000000000000000000000000000000000000000000000000000000000000000000000000000010200000000000000000000000000000000000000000000000000000000000000000000000000000000000000000000000000000000000000000000000000000000000000000000080000000000000000008000000000000000000000000000000000000000000000000000000000000000000000\",\n    \"blockHash\": \"0x7cf6f550514cf805feb58dfadb10fbeacfad350c55bbcbd88ba0e02d234a3cb2\",\n    \"transactionHash\": \"0xdceeb6a92cf4e447c6c7c592eb04c30cedc9cc39cc9b2b16238e0f8121a013ff\",\n    \"logs\": [\n      {\n        \"transactionIndex\": 0,\n        \"blockNumber\": 67241,\n        \"transactionHash\": \"0xdceeb6a92cf4e447c6c7c592eb04c30cedc9cc39cc9b2b16238e0f8121a013ff\",\n        \"address\": \"0x3F0AD83d1e0Ae510eb7764B52Ef21be12BEB7d3C\",\n        \"topics\": [\n          \"0xa6f2e38f0cfebf27212317fced3ac40bc62e00bd33f38d69603710740c69acb7\"\n        ],\n        \"data\": \"0x00000000000000000000000026b67d8a29a31d24ce57dc0c550c7f0d134f6ff0\",\n        \"logIndex\": 0,\n        \"blockHash\": \"0x7cf6f550514cf805feb58dfadb10fbeacfad350c55bbcbd88ba0e02d234a3cb2\",\n        \"transactionLogIndex\": 0,\n        \"name\": \"SetContentContract\",\n        \"signature\": \"SetContentContract(address)\",\n        \"topic\": \"0xa6f2e38f0cfebf27212317fced3ac40bc62e00bd33f38d69603710740c69acb7\",\n        \"values\": {\n          \"0\": \"0x26b67d8A29A31d24CE57dC0C550c7f0D134f6fF0\",\n          \"contentContractAddress\": \"0x26b67d8A29A31d24CE57dC0C550c7f0D134f6fF0\",\n          \"length\": 1\n        }\n      }\n    ],\n    \"blockNumber\": 67241,\n    \"confirmations\": 1,\n    \"cumulativeGasUsed\": {\n      \"_hex\": \"0x1837a\"\n    }\n  },\n  \"eventName\": \"SetContentContract\"\n});",
    "result": {
      "name": "SetContentContract",
      "signature": "SetContentContract(address)",
      "topic": "0xa6f2e38f0cfebf27212317fced3ac40bc62e00bd33f38d69603710740c69acb7",
      "values": {
        "0": "0x26b67d8A29A31d24CE57dC0C550c7f0D134f6fF0",
        "contentContractAddress": "0x26b67d8A29A31d24CE57dC0C550c7f0D134f6fF0",
        "length": 1
      }
    }
  },
  {
    "signature": "async ExtractEventFromLogs({\n  \"abi\": [\n    {\n      \"constant\": true,\n      \"inputs\": [],\n      \"name\": \"STATUS_PUBLISHED\",\n      \"outputs\": [\n        {\n          \"name\": \"\",\n          \"type\": \"bytes32\"\n        }\n      ],\n      \"payable\": false,\n      \"stateMutability\": \"view\",\n      \"type\": \"function\"\n    },\n    {\n      \"constant\": true,\n      \"inputs\": [],\n      \"name\": \"creator\",\n      \"outputs\": [\n        {\n          \"name\": \"\",\n          \"type\": \"address\"\n        }\n      ],\n      \"payable\": false,\n      \"stateMutability\": \"view\",\n      \"type\": \"function\"\n    },\n    {\n      \"constant\": false,\n      \"inputs\": [],\n      \"name\": \"publish\",\n      \"outputs\": [\n        {\n          \"name\": \"\",\n          \"type\": \"bool\"\n        }\n      ],\n      \"payable\": true,\n      \"stateMutability\": \"payable\",\n      \"type\": \"function\"\n    },\n    {\n      \"constant\": true,\n      \"inputs\": [\n        {\n          \"name\": \"\",\n          \"type\": \"uint256\"\n        }\n      ],\n      \"name\": \"requestMap\",\n      \"outputs\": [\n        {\n          \"name\": \"originator\",\n          \"type\": \"address\"\n        },\n        {\n          \"name\": \"amountPaid\",\n          \"type\": \"uint256\"\n        },\n        {\n          \"name\": \"status\",\n          \"type\": \"int8\"\n        }\n      ],\n      \"payable\": false,\n      \"stateMutability\": \"view\",\n      \"type\": \"function\"\n    },\n    {\n      \"constant\": true,\n      \"inputs\": [],\n      \"name\": \"contentContractAddress\",\n      \"outputs\": [\n        {\n          \"name\": \"\",\n          \"type\": \"address\"\n        }\n      ],\n      \"payable\": false,\n      \"stateMutability\": \"view\",\n      \"type\": \"function\"\n    },\n    {\n      \"constant\": true,\n      \"inputs\": [],\n      \"name\": \"statusCode\",\n      \"outputs\": [\n        {\n          \"name\": \"\",\n          \"type\": \"int256\"\n        }\n      ],\n      \"payable\": false,\n      \"stateMutability\": \"view\",\n      \"type\": \"function\"\n    },\n    {\n      \"constant\": true,\n      \"inputs\": [],\n      \"name\": \"addressKMS\",\n      \"outputs\": [\n        {\n          \"name\": \"\",\n          \"type\": \"address\"\n        }\n      ],\n      \"payable\": false,\n      \"stateMutability\": \"view\",\n      \"type\": \"function\"\n    },\n    {\n      \"constant\": true,\n      \"inputs\": [],\n      \"name\": \"contentType\",\n      \"outputs\": [\n        {\n          \"name\": \"\",\n          \"type\": \"address\"\n        }\n      ],\n      \"payable\": false,\n      \"stateMutability\": \"view\",\n      \"type\": \"function\"\n    },\n    {\n      \"constant\": true,\n      \"inputs\": [\n        {\n          \"name\": \"status_code\",\n          \"type\": \"int256\"\n        }\n      ],\n      \"name\": \"statusCodeDescription\",\n      \"outputs\": [\n        {\n          \"name\": \"\",\n          \"type\": \"bytes32\"\n        }\n      ],\n      \"payable\": false,\n      \"stateMutability\": \"view\",\n      \"type\": \"function\"\n    },\n    {\n      \"constant\": false,\n      \"inputs\": [],\n      \"name\": \"kill\",\n      \"outputs\": [],\n      \"payable\": false,\n      \"stateMutability\": \"nonpayable\",\n      \"type\": \"function\"\n    },\n    {\n      \"constant\": true,\n      \"inputs\": [],\n      \"name\": \"STATUS_DRAFT\",\n      \"outputs\": [\n        {\n          \"name\": \"\",\n          \"type\": \"bytes32\"\n        }\n      ],\n      \"payable\": false,\n      \"stateMutability\": \"view\",\n      \"type\": \"function\"\n    },\n    {\n      \"constant\": false,\n      \"inputs\": [\n        {\n          \"name\": \"status_code\",\n          \"type\": \"int256\"\n        }\n      ],\n      \"name\": \"setStatusCode\",\n      \"outputs\": [\n        {\n          \"name\": \"\",\n          \"type\": \"int256\"\n        }\n      ],\n      \"payable\": false,\n      \"stateMutability\": \"nonpayable\",\n      \"type\": \"function\"\n    },\n    {\n      \"constant\": false,\n      \"inputs\": [\n        {\n          \"name\": \"request_ID\",\n          \"type\": \"uint256\"\n        },\n        {\n          \"name\": \"score_pct\",\n          \"type\": \"uint256\"\n        },\n        {\n          \"name\": \"ml_out_hash\",\n          \"type\": \"bytes32\"\n        }\n      ],\n      \"name\": \"accessComplete\",\n      \"outputs\": [\n        {\n          \"name\": \"\",\n          \"type\": \"bool\"\n        }\n      ],\n      \"payable\": true,\n      \"stateMutability\": \"payable\",\n      \"type\": \"function\"\n    },\n    {\n      \"constant\": true,\n      \"inputs\": [],\n      \"name\": \"accessCharge\",\n      \"outputs\": [\n        {\n          \"name\": \"\",\n          \"type\": \"uint256\"\n        }\n      ],\n      \"payable\": false,\n      \"stateMutability\": \"view\",\n      \"type\": \"function\"\n    },\n    {\n      \"constant\": false,\n      \"inputs\": [\n        {\n          \"name\": \"newCreator\",\n          \"type\": \"address\"\n        }\n      ],\n      \"name\": \"transferCreatorship\",\n      \"outputs\": [],\n      \"payable\": false,\n      \"stateMutability\": \"nonpayable\",\n      \"type\": \"function\"\n    },\n    {\n      \"constant\": false,\n      \"inputs\": [\n        {\n          \"name\": \"status_code\",\n          \"type\": \"int256\"\n        }\n      ],\n      \"name\": \"updateStatus\",\n      \"outputs\": [\n        {\n          \"name\": \"\",\n          \"type\": \"int256\"\n        }\n      ],\n      \"payable\": false,\n      \"stateMutability\": \"nonpayable\",\n      \"type\": \"function\"\n    },\n    {\n      \"constant\": false,\n      \"inputs\": [\n        {\n          \"name\": \"level\",\n          \"type\": \"uint8\"\n        },\n        {\n          \"name\": \"custom_values\",\n          \"type\": \"bytes32[]\"\n        },\n        {\n          \"name\": \"stakeholders\",\n          \"type\": \"address[]\"\n        }\n      ],\n      \"name\": \"getAccessCharge\",\n      \"outputs\": [\n        {\n          \"name\": \"\",\n          \"type\": \"uint256\"\n        }\n      ],\n      \"payable\": false,\n      \"stateMutability\": \"nonpayable\",\n      \"type\": \"function\"\n    },\n    {\n      \"constant\": true,\n      \"inputs\": [],\n      \"name\": \"owner\",\n      \"outputs\": [\n        {\n          \"name\": \"\",\n          \"type\": \"address\"\n        }\n      ],\n      \"payable\": false,\n      \"stateMutability\": \"view\",\n      \"type\": \"function\"\n    },\n    {\n      \"constant\": true,\n      \"inputs\": [],\n      \"name\": \"requestID\",\n      \"outputs\": [\n        {\n          \"name\": \"\",\n          \"type\": \"uint256\"\n        }\n      ],\n      \"payable\": false,\n      \"stateMutability\": \"view\",\n      \"type\": \"function\"\n    },\n    {\n      \"constant\": false,\n      \"inputs\": [\n        {\n          \"name\": \"level\",\n          \"type\": \"uint8\"\n        },\n        {\n          \"name\": \"pke_requestor\",\n          \"type\": \"string\"\n        },\n        {\n          \"name\": \"pke_AFGH\",\n          \"type\": \"string\"\n        },\n        {\n          \"name\": \"custom_values\",\n          \"type\": \"bytes32[]\"\n        },\n        {\n          \"name\": \"stakeholders\",\n          \"type\": \"address[]\"\n        }\n      ],\n      \"name\": \"accessRequest\",\n      \"outputs\": [\n        {\n          \"name\": \"\",\n          \"type\": \"bool\"\n        }\n      ],\n      \"payable\": true,\n      \"stateMutability\": \"payable\",\n      \"type\": \"function\"\n    },\n    {\n      \"constant\": true,\n      \"inputs\": [],\n      \"name\": \"libraryAddress\",\n      \"outputs\": [\n        {\n          \"name\": \"\",\n          \"type\": \"address\"\n        }\n      ],\n      \"payable\": false,\n      \"stateMutability\": \"view\",\n      \"type\": \"function\"\n    },\n    {\n      \"constant\": false,\n      \"inputs\": [],\n      \"name\": \"updateRequest\",\n      \"outputs\": [],\n      \"payable\": false,\n      \"stateMutability\": \"nonpayable\",\n      \"type\": \"function\"\n    },\n    {\n      \"constant\": false,\n      \"inputs\": [\n        {\n          \"name\": \"address_KMS\",\n          \"type\": \"address\"\n        }\n      ],\n      \"name\": \"setAddressKMS\",\n      \"outputs\": [],\n      \"payable\": false,\n      \"stateMutability\": \"nonpayable\",\n      \"type\": \"function\"\n    },\n    {\n      \"constant\": true,\n      \"inputs\": [],\n      \"name\": \"STATUS_REVIEW\",\n      \"outputs\": [\n        {\n          \"name\": \"\",\n          \"type\": \"bytes32\"\n        }\n      ],\n      \"payable\": false,\n      \"stateMutability\": \"view\",\n      \"type\": \"function\"\n    },\n    {\n      \"constant\": true,\n      \"inputs\": [],\n      \"name\": \"objectHash\",\n      \"outputs\": [\n        {\n          \"name\": \"\",\n          \"type\": \"bytes32\"\n        }\n      ],\n      \"payable\": false,\n      \"stateMutability\": \"view\",\n      \"type\": \"function\"\n    },\n    {\n      \"constant\": false,\n      \"inputs\": [\n        {\n          \"name\": \"addr\",\n          \"type\": \"address\"\n        }\n      ],\n      \"name\": \"setContentContractAddress\",\n      \"outputs\": [],\n      \"payable\": false,\n      \"stateMutability\": \"nonpayable\",\n      \"type\": \"function\"\n    },\n    {\n      \"constant\": false,\n      \"inputs\": [\n        {\n          \"name\": \"request_ID\",\n          \"type\": \"uint256\"\n        },\n        {\n          \"name\": \"access_granted\",\n          \"type\": \"bool\"\n        },\n        {\n          \"name\": \"re_key\",\n          \"type\": \"string\"\n        },\n        {\n          \"name\": \"encrypted_AES_key\",\n          \"type\": \"string\"\n        }\n      ],\n      \"name\": \"accessGrant\",\n      \"outputs\": [\n        {\n          \"name\": \"\",\n          \"type\": \"bool\"\n        }\n      ],\n      \"payable\": false,\n      \"stateMutability\": \"nonpayable\",\n      \"type\": \"function\"\n    },\n    {\n      \"constant\": false,\n      \"inputs\": [\n        {\n          \"name\": \"object_hash\",\n          \"type\": \"bytes32\"\n        }\n      ],\n      \"name\": \"commit\",\n      \"outputs\": [],\n      \"payable\": false,\n      \"stateMutability\": \"nonpayable\",\n      \"type\": \"function\"\n    },\n    {\n      \"constant\": false,\n      \"inputs\": [\n        {\n          \"name\": \"newOwner\",\n          \"type\": \"address\"\n        }\n      ],\n      \"name\": \"transferOwnership\",\n      \"outputs\": [],\n      \"payable\": false,\n      \"stateMutability\": \"nonpayable\",\n      \"type\": \"function\"\n    },\n    {\n      \"constant\": false,\n      \"inputs\": [\n        {\n          \"name\": \"charge\",\n          \"type\": \"uint256\"\n        }\n      ],\n      \"name\": \"setAccessCharge\",\n      \"outputs\": [\n        {\n          \"name\": \"\",\n          \"type\": \"uint256\"\n        }\n      ],\n      \"payable\": false,\n      \"stateMutability\": \"nonpayable\",\n      \"type\": \"function\"\n    },\n    {\n      \"constant\": true,\n      \"inputs\": [],\n      \"name\": \"statusDescription\",\n      \"outputs\": [\n        {\n          \"name\": \"\",\n          \"type\": \"bytes32\"\n        }\n      ],\n      \"payable\": false,\n      \"stateMutability\": \"view\",\n      \"type\": \"function\"\n    },\n    {\n      \"inputs\": [\n        {\n          \"name\": \"content_type\",\n          \"type\": \"address\"\n        }\n      ],\n      \"payable\": true,\n      \"stateMutability\": \"payable\",\n      \"type\": \"constructor\"\n    },\n    {\n      \"payable\": true,\n      \"stateMutability\": \"payable\",\n      \"type\": \"fallback\"\n    },\n    {\n      \"anonymous\": false,\n      \"inputs\": [\n        {\n          \"indexed\": false,\n          \"name\": \"containingLibrary\",\n          \"type\": \"address\"\n        }\n      ],\n      \"name\": \"ContentObjectCreate\",\n      \"type\": \"event\"\n    },\n    {\n      \"anonymous\": false,\n      \"inputs\": [\n        {\n          \"indexed\": false,\n          \"name\": \"contentType\",\n          \"type\": \"address\"\n        },\n        {\n          \"indexed\": false,\n          \"name\": \"contentContractAddress\",\n          \"type\": \"address\"\n        }\n      ],\n      \"name\": \"SetContentType\",\n      \"type\": \"event\"\n    },\n    {\n      \"anonymous\": false,\n      \"inputs\": [\n        {\n          \"indexed\": false,\n          \"name\": \"requestID\",\n          \"type\": \"uint256\"\n        },\n        {\n          \"indexed\": false,\n          \"name\": \"level\",\n          \"type\": \"uint8\"\n        },\n        {\n          \"indexed\": false,\n          \"name\": \"contentHash\",\n          \"type\": \"bytes32\"\n        },\n        {\n          \"indexed\": false,\n          \"name\": \"pkeRequestor\",\n          \"type\": \"string\"\n        },\n        {\n          \"indexed\": false,\n          \"name\": \"pkeAFGH\",\n          \"type\": \"string\"\n        }\n      ],\n      \"name\": \"AccessRequest\",\n      \"type\": \"event\"\n    },\n    {\n      \"anonymous\": false,\n      \"inputs\": [\n        {\n          \"indexed\": false,\n          \"name\": \"requestID\",\n          \"type\": \"uint256\"\n        },\n        {\n          \"indexed\": false,\n          \"name\": \"access_granted\",\n          \"type\": \"bool\"\n        },\n        {\n          \"indexed\": false,\n          \"name\": \"reKey\",\n          \"type\": \"string\"\n        },\n        {\n          \"indexed\": false,\n          \"name\": \"encryptedAESKey\",\n          \"type\": \"string\"\n        }\n      ],\n      \"name\": \"AccessGrant\",\n      \"type\": \"event\"\n    },\n    {\n      \"anonymous\": false,\n      \"inputs\": [\n        {\n          \"indexed\": false,\n          \"name\": \"customValue\",\n          \"type\": \"bytes32\"\n        }\n      ],\n      \"name\": \"AccessRequestValue\",\n      \"type\": \"event\"\n    },\n    {\n      \"anonymous\": false,\n      \"inputs\": [\n        {\n          \"indexed\": false,\n          \"name\": \"stakeholder\",\n          \"type\": \"address\"\n        }\n      ],\n      \"name\": \"AccessRequestStakeholder\",\n      \"type\": \"event\"\n    },\n    {\n      \"anonymous\": false,\n      \"inputs\": [\n        {\n          \"indexed\": false,\n          \"name\": \"requestID\",\n          \"type\": \"uint256\"\n        },\n        {\n          \"indexed\": false,\n          \"name\": \"scorePct\",\n          \"type\": \"uint256\"\n        },\n        {\n          \"indexed\": false,\n          \"name\": \"mlOutHash\",\n          \"type\": \"bytes32\"\n        },\n        {\n          \"indexed\": false,\n          \"name\": \"customContractResult\",\n          \"type\": \"bool\"\n        }\n      ],\n      \"name\": \"AccessComplete\",\n      \"type\": \"event\"\n    },\n    {\n      \"anonymous\": false,\n      \"inputs\": [\n        {\n          \"indexed\": false,\n          \"name\": \"contentContractAddress\",\n          \"type\": \"address\"\n        }\n      ],\n      \"name\": \"SetContentContract\",\n      \"type\": \"event\"\n    },\n    {\n      \"anonymous\": false,\n      \"inputs\": [\n        {\n          \"indexed\": false,\n          \"name\": \"accessCharge\",\n          \"type\": \"uint256\"\n        }\n      ],\n      \"name\": \"SetAccessCharge\",\n      \"type\": \"event\"\n    },\n    {\n      \"anonymous\": false,\n      \"inputs\": [\n        {\n          \"indexed\": false,\n          \"name\": \"level\",\n          \"type\": \"uint8\"\n        },\n        {\n          \"indexed\": false,\n          \"name\": \"accessCharge\",\n          \"type\": \"uint256\"\n        }\n      ],\n      \"name\": \"GetAccessCharge\",\n      \"type\": \"event\"\n    },\n    {\n      \"anonymous\": false,\n      \"inputs\": [\n        {\n          \"indexed\": false,\n          \"name\": \"accessCharge\",\n          \"type\": \"uint256\"\n        },\n        {\n          \"indexed\": false,\n          \"name\": \"amountProvided\",\n          \"type\": \"uint256\"\n        }\n      ],\n      \"name\": \"InsufficientFunds\",\n      \"type\": \"event\"\n    },\n    {\n      \"anonymous\": false,\n      \"inputs\": [\n        {\n          \"indexed\": false,\n          \"name\": \"statusCode\",\n          \"type\": \"int256\"\n        }\n      ],\n      \"name\": \"SetStatusCode\",\n      \"type\": \"event\"\n    },\n    {\n      \"anonymous\": false,\n      \"inputs\": [\n        {\n          \"indexed\": false,\n          \"name\": \"requestStatus\",\n          \"type\": \"bool\"\n        },\n        {\n          \"indexed\": false,\n          \"name\": \"statusCode\",\n          \"type\": \"int256\"\n        },\n        {\n          \"indexed\": false,\n          \"name\": \"objectHash\",\n          \"type\": \"bytes32\"\n        }\n      ],\n      \"name\": \"Publish\",\n      \"type\": \"event\"\n    },\n    {\n      \"anonymous\": false,\n      \"inputs\": [\n        {\n          \"indexed\": false,\n          \"name\": \"custom_contract\",\n          \"type\": \"address\"\n        }\n      ],\n      \"name\": \"InvokeCustomPreHook\",\n      \"type\": \"event\"\n    },\n    {\n      \"anonymous\": false,\n      \"inputs\": [\n        {\n          \"indexed\": false,\n          \"name\": \"custom_contract\",\n          \"type\": \"address\"\n        },\n        {\n          \"indexed\": false,\n          \"name\": \"result\",\n          \"type\": \"uint256\"\n        }\n      ],\n      \"name\": \"ReturnCustomHook\",\n      \"type\": \"event\"\n    },\n    {\n      \"anonymous\": false,\n      \"inputs\": [\n        {\n          \"indexed\": false,\n          \"name\": \"custom_contract\",\n          \"type\": \"address\"\n        }\n      ],\n      \"name\": \"InvokeCustomPostHook\",\n      \"type\": \"event\"\n    },\n    {\n      \"anonymous\": false,\n      \"inputs\": [\n        {\n          \"indexed\": false,\n          \"name\": \"objectHash\",\n          \"type\": \"bytes32\"\n        }\n      ],\n      \"name\": \"Commit\",\n      \"type\": \"event\"\n    },\n    {\n      \"anonymous\": false,\n      \"inputs\": [\n        {\n          \"indexed\": false,\n          \"name\": \"objectHash\",\n          \"type\": \"bytes32\"\n        }\n      ],\n      \"name\": \"UpdateRequest\",\n      \"type\": \"event\"\n    }\n  ],\n  \"event\": {\n    \"to\": \"0x3F0AD83d1e0Ae510eb7764B52Ef21be12BEB7d3C\",\n    \"from\": \"0xf7C6072c6d61305000E33fF8D8735b3C6af7e10D\",\n    \"contractAddress\": null,\n    \"transactionIndex\": 0,\n    \"root\": \"0xb5f254b0ee469972a5f28dc3bcce5e46895687f5ab69a7bfc30cea8c9614c4f6\",\n    \"gasUsed\": {\n      \"_hex\": \"0x13fcd\"\n    },\n    \"logsBloom\": \"0x00000000000000000000000000000000000000000000000000000000000000000000000000000000000000000000000000000000000000000000000000000000000000000000000004000000000000000000000000000000000000000000000000400000000000000000000000000000000000000000000000000000000000000000000000000000000000000200000000000000000000000000000000000000000000000000000000000000000000000000000000000000000000000000000000000000000000000000000000000000000000080000000000000000008000000000000000000000000000000000000000000000000000000000002000000000\",\n    \"blockHash\": \"0x96c2e0e00e989a281fb92a5cd5d9489bec566feecfdb730daaf750ea3f876ad7\",\n    \"transactionHash\": \"0x96da9402c63977fac168a78ac7e4be728fc0ba82abd71b1178ac7fc12a801d17\",\n    \"logs\": [\n      {\n        \"transactionIndex\": 0,\n        \"blockNumber\": 67243,\n        \"transactionHash\": \"0x96da9402c63977fac168a78ac7e4be728fc0ba82abd71b1178ac7fc12a801d17\",\n        \"address\": \"0x3F0AD83d1e0Ae510eb7764B52Ef21be12BEB7d3C\",\n        \"topics\": [\n          \"0x089a6f1788a3c353423e1be4ba12533bdde7d908bb41abeee185af0acb3df562\"\n        ],\n        \"data\": \"0x00000000000000000000000000000000000000000000000000000000000000030000000000000000000000000000000000000000000000000000000000000000000000000000000000000000000000000000000000000000000000000000000000000000000000000000000000000000000000000000000000000000000000a000000000000000000000000000000000000000000000000000000000000001600000000000000000000000000000000000000000000000000000000000000084307830343036343864643165323761396261336131393937323766343864323765373139363363303465356164363334386337383864626635346236373733663933396437663933396437343932616163613137613731646233393630376664333436383561306639353564353234353961323130386533376364663030373834616532000000000000000000000000000000000000000000000000000000000000000000000000000000000000000000000000000000000000000000000000\",\n        \"logIndex\": 0,\n        \"blockHash\": \"0x96c2e0e00e989a281fb92a5cd5d9489bec566feecfdb730daaf750ea3f876ad7\",\n        \"transactionLogIndex\": 0,\n        \"name\": \"AccessRequest\",\n        \"signature\": \"AccessRequest(uint256,uint8,bytes32,string,string)\",\n        \"topic\": \"0x089a6f1788a3c353423e1be4ba12533bdde7d908bb41abeee185af0acb3df562\",\n        \"values\": {\n          \"0\": {\n            \"_hex\": \"0x03\"\n          },\n          \"1\": 0,\n          \"2\": \"0x0000000000000000000000000000000000000000000000000000000000000000\",\n          \"3\": \"0x040648dd1e27a9ba3a199727f48d27e71963c04e5ad6348c788dbf54b6773f939d7f939d7492aaca17a71db39607fd34685a0f955d52459a2108e37cdf00784ae2\",\n          \"4\": \"\",\n          \"requestID\": {\n            \"_hex\": \"0x03\"\n          },\n          \"level\": 0,\n          \"contentHash\": \"0x0000000000000000000000000000000000000000000000000000000000000000\",\n          \"pkeRequestor\": \"0x040648dd1e27a9ba3a199727f48d27e71963c04e5ad6348c788dbf54b6773f939d7f939d7492aaca17a71db39607fd34685a0f955d52459a2108e37cdf00784ae2\",\n          \"pkeAFGH\": \"\",\n          \"length\": 5\n        }\n      }\n    ],\n    \"blockNumber\": 67243,\n    \"confirmations\": 1,\n    \"cumulativeGasUsed\": {\n      \"_hex\": \"0x13fcd\"\n    }\n  },\n  \"eventName\": \"AccessRequest\"\n});",
    "result": {
      "name": "AccessRequest",
      "signature": "AccessRequest(uint256,uint8,bytes32,string,string)",
      "topic": "0x089a6f1788a3c353423e1be4ba12533bdde7d908bb41abeee185af0acb3df562",
      "values": {
        "0": {
          "_hex": "0x03"
        },
        "1": 0,
        "2": "0x0000000000000000000000000000000000000000000000000000000000000000",
        "3": "0x040648dd1e27a9ba3a199727f48d27e71963c04e5ad6348c788dbf54b6773f939d7f939d7492aaca17a71db39607fd34685a0f955d52459a2108e37cdf00784ae2",
        "4": "",
        "requestID": {
          "_hex": "0x03"
        },
        "level": 0,
        "contentHash": "0x0000000000000000000000000000000000000000000000000000000000000000",
        "pkeRequestor": "0x040648dd1e27a9ba3a199727f48d27e71963c04e5ad6348c788dbf54b6773f939d7f939d7492aaca17a71db39607fd34685a0f955d52459a2108e37cdf00784ae2",
        "pkeAFGH": "",
        "length": 5
      }
    }
  }
]